[
	{
		"TYPE": "DEMO",
		"UNK0": "00001000",
		"SCRIPT_ID": 11231,
		"UNK1": "01000000"
	},
	{
		"TYPE": "CI_LOAD",
		"UNK0": "10000c00524e0500"
	},
	{
		"TYPE": "CI_LOAD_WAIT",
		"UNK0": "0c000a000500"
	},
	{
		"TYPE": "CI_LOAD",
		"UNK0": "0c000c00524e0400"
	},
	{
		"TYPE": "CI_LOAD_WAIT",
		"UNK0": "0c000a000400"
	},
	{
		"TYPE": "BG_LOAD",
		"UNK0": "0c000c00e70c0300"
	},
	{
		"TYPE": "BG_LOAD",
		"UNK0": "0c000c0089130400"
	},
	{
		"TYPE": "CI_LOAD",
		"UNK0": "0c000c009c130300"
	},
	{
		"TYPE": "BG_LOAD",
		"UNK0": "0c000c0059020200"
	},
	{
		"TYPE": "CI_LOAD",
		"UNK0": "0c000c00800c0200"
	},
	{
		"TYPE": "CI_LOAD",
		"UNK0": "0c000c009c130100"
	},
	{
		"TYPE": "CI_LOAD",
		"UNK0": "0c000c00800c0000"
	},
	{
		"TYPE": "MSG_READY",
		"UNK0": "0c000c000000b303"
	},
	{
		"TYPE": "BG_LOAD",
		"UNK0": "0c000c00c8000100"
	},
	{
		"TYPE": "LOOPS_READY",
		"UNK0": "0c000c00ff020000"
	},
	{
		"TYPE": "BG_LOAD",
		"UNK0": "0c000c0089130000"
	},
	{
		"TYPE": "BG_WAIT",
		"UNK0": "0c000a000000"
	},
	{
		"TYPE": "BG_SET_ADJUST_Z",
		"UNK0": "0c000c0000000000"
	},
	{
		"TYPE": "BG_FADE",
		"UNK0": "0c001000ffffffff00000000"
	},
	{
		"TYPE": "CALL_DEMO",
		"UNK0": "10001c00a51f000000000000000000000000000000000000"
	},
	{
		"TYPE": "WAIT_DEMO_ALL",
		"UNK0": "1c000800"
	},
	{
		"TYPE": "SCR_FADE",
		"UNK0": "08001000000000000a000000"
	},
	{
		"TYPE": "WAIT",
		"UNK0": "10000a000a00"
	},
	{
		"TYPE": "TXTWND_IN",
		"UNK0": "0c000a001400"
	},
	{
		"TYPE": "WAIT",
		"UNK0": "0c000a001e00"
	},
	{
		"TYPE": "PAGE",
		"UNK0": "0c000e0000000b000000"
	},
	{
		"STRINGS": [
			"そして、その夜——"
		]
	},
	{
		"TYPE": "BR",
		"UNK0": "24000a000103"
	},
	{
		"TYPE": "PAGEtm",
		"UNK0": "0c000800"
	},
	{
		"TYPE": "EXTEND",
		"UNK0": "0800180002000000000000000000000000000000"
	},
	{
		"TYPE": "TXTWND_OUT",
		"UNK0": "18000a001400"
	},
	{
		"TYPE": "WAIT",
		"UNK0": "0c000a001e00"
	},
	{
		"TYPE": "SE_PLAY",
		"UNK0": "0c000e00350180800000"
	},
	{
		"TYPE": "WAIT",
		"UNK0": "10000a001e00"
	},
	{
		"TYPE": "LOOPS_WAIT",
		"UNK0": "0c000a000000"
	},
	{
		"TYPE": "LOOPS_PLAY",
		"UNK0": "0c001000ff02000000000000"
	},
	{
		"TYPE": "LOOPS_VOL",
		"UNK0": "10000e0046003c000000"
	},
	{
		"TYPE": "WAIT",
		"UNK0": "10000a004600"
	},
	{
		"TYPE": "SE_PLAY",
		"UNK0": "0c000e00a80080800000"
	},
	{
		"TYPE": "WAIT",
		"UNK0": "10000a002c01"
	},
	{
		"TYPE": "SE_PLAY",
		"UNK0": "0c000e00a70080800000"
	},
	{
		"TYPE": "BG_WAIT",
		"UNK0": "10000a000100"
	},
	{
		"TYPE": "BG_SET_ADJUST_Z",
		"UNK0": "0c000c0001000100"
	},
	{
		"TYPE": "BG_FADE",
		"UNK0": "0c001000808080805a000100"
	},
	{
		"TYPE": "WAIT",
		"UNK0": "10000a005a00"
	},
	{
		"TYPE": "TXTWND_IN",
		"UNK0": "0c000a001400"
	},
	{
		"TYPE": "WAIT",
		"UNK0": "0c000a001e00"
	},
	{
		"TYPE": "PAGE",
		"UNK0": "0c000e0000000b000100"
	},
	{
		"TYPE": "SPEAKER",
		"UNK0": "10000a00",
		"CHARACTER_ID": 12,
		"NAME": "Official"
	},
	{
		"STRINGS": [
			"\"関本爽二朗、起立して、奥の壁に手をつけ！！\""
		]
	},
	{
		"TYPE": "BR",
		"UNK0": "3c000a000103"
	},
	{
		"TYPE": "PAGEtm",
		"UNK0": "0c000800"
	},
	{
		"TYPE": "EXTEND",
		"UNK0": "0800180002000000000000000000000000000000"
	},
	{
		"TYPE": "WAIT",
		"UNK0": "18000a001e00"
	},
	{
		"TYPE": "PAGE",
		"UNK0": "0c000e0000000b000200"
	},
	{
		"TYPE": "SPEAKER",
		"UNK0": "10000a00",
		"CHARACTER_ID": 3,
		"NAME": "Sekimoto Soujirou"
	},
	{
		"STRINGS": [
			"\"…………\""
		]
	},
	{
		"TYPE": "BR",
		"UNK0": "18000a000103"
	},
	{
		"TYPE": "PAGEtm",
		"UNK0": "0c000800"
	},
	{
		"TYPE": "EXTEND",
		"UNK0": "0800180002000000000000000000000000000000"
	},
	{
		"TYPE": "WAIT",
		"UNK0": "18000a001e00"
	},
	{
		"TYPE": "BG_FADE",
		"UNK0": "0c0010000000000000000000"
	},
	{
		"TYPE": "BG_MOVE",
		"UNK0": "1000120000000000d00700000000"
	},
	{
		"TYPE": "BG_SET_ADJUST_Z",
		"UNK0": "14000c0000000000"
	},
	{
		"TYPE": "BG_LOAD",
		"UNK0": "0c000c00490d0000"
	},
	{
		"TYPE": "PAGE",
		"UNK0": "0c000e0000000b000300"
	},
	{
		"STRINGS": [
			"彼は署員の言う事に素直に従い、",
			"奥の壁に手をついて、私達に背中を向けた。"
		]
	},
	{
		"TYPE": "BR",
		"UNK0": "34000a000103"
	},
	{
		"TYPE": "PAGEtm",
		"UNK0": "0c000800"
	},
	{
		"TYPE": "PAGE",
		"UNK0": "08000e0000000b000400"
	},
	{
		"TYPE": "SPEAKER",
		"UNK0": "10000a00",
		"CHARACTER_ID": 12,
		"NAME": "Official"
	},
	{
		"STRINGS": [
			"\"収容員、壁付き確認！\""
		]
	},
	{
		"TYPE": "BR",
		"UNK0": "24000a000103"
	},
	{
		"TYPE": "PAGEtm",
		"UNK0": "0c000800"
	},
	{
		"TYPE": "PAGE",
		"UNK0": "08000e0000000b000500"
	},
	{
		"TYPE": "SPEAKER",
		"UNK0": "10000a00",
		"CHARACTER_ID": 12,
		"NAME": "Official"
	},
	{
		"STRINGS": [
			"\"壁付き確認！！　解錠！！\""
		]
	},
	{
		"TYPE": "BR",
		"UNK0": "28000a000103"
	},
	{
		"TYPE": "PAGEtm",
		"UNK0": "0c000800"
	},
	{
		"TYPE": "EXTEND",
		"UNK0": "0800180002000000000000000000000000000000"
	},
	{
		"TYPE": "EXTEND",
		"UNK0": "1800180002000000000000000000000000000000"
	},
	{
		"TYPE": "TXTWND_OUT",
		"UNK0": "18000a001400"
	},
	{
		"TYPE": "WAIT",
		"UNK0": "0c000a001e00"
	},
	{
		"TYPE": "SE_PLAY",
		"UNK0": "0c000e004b0180800000"
	},
	{
		"TYPE": "WAIT",
		"UNK0": "10000a006400"
	},
	{
		"TYPE": "TXTWND_IN",
		"UNK0": "0c000a001400"
	},
	{
		"TYPE": "WAIT",
		"UNK0": "0c000a001e00"
	},
	{
		"TYPE": "PAGE",
		"UNK0": "0c000e0000000b000600"
	},
	{
		"TYPE": "SPEAKER",
		"UNK0": "10000a00",
		"CHARACTER_ID": 12,
		"NAME": "Official"
	},
	{
		"STRINGS": [
			"\"解錠確認！\""
		]
	},
	{
		"TYPE": "BR",
		"UNK0": "1c000a000103"
	},
	{
		"TYPE": "PAGEtm",
		"UNK0": "0c000800"
	},
	{
		"TYPE": "PAGE",
		"UNK0": "08000e0000000b000700"
	},
	{
		"TYPE": "SPEAKER",
		"UNK0": "10000a00",
		"CHARACTER_ID": 12,
		"NAME": "Official"
	},
	{
		"STRINGS": [
			"\"解錠確認！　扉を開けよ！！\""
		]
	},
	{
		"TYPE": "BR",
		"UNK0": "2c000a000103"
	},
	{
		"TYPE": "PAGEtm",
		"UNK0": "0c000800"
	},
	{
		"TYPE": "EXTEND",
		"UNK0": "0800180002000000000000000000000000000000"
	},
	{
		"TYPE": "EXTEND",
		"UNK0": "1800180002000000000000000000000000000000"
	},
	{
		"TYPE": "TXTWND_OUT",
		"UNK0": "18000a001400"
	},
	{
		"TYPE": "WAIT",
		"UNK0": "0c000a001e00"
	},
	{
		"TYPE": "SE_PLAY",
		"UNK0": "0c000e003d0180800000"
	},
	{
		"TYPE": "WAIT",
		"UNK0": "10000a00c800"
	},
	{
		"TYPE": "TXTWND_IN",
		"UNK0": "0c000a001400"
	},
	{
		"TYPE": "WAIT",
		"UNK0": "0c000a001e00"
	},
	{
		"TYPE": "PAGE",
		"UNK0": "0c000e0000000b000800"
	},
	{
		"STRINGS": [
			"二人一組の署員が、マニュアルに忠実な動きで、",
			"行動を続けている。",
			"私と黒田課長は、彼らの動きを静かに見守っていた。"
		]
	},
	{
		"TYPE": "BR",
		"UNK0": "3c000a000103"
	},
	{
		"TYPE": "PAGEtm",
		"UNK0": "0c000800"
	},
	{
		"TYPE": "PAGE",
		"UNK0": "08000e0000000b000900"
	},
	{
		"STRINGS": [
			"黒田課長も、内心複雑な表情をわずかに見せていた。"
		]
	},
	{
		"TYPE": "BR",
		"UNK0": "40000a000103"
	},
	{
		"TYPE": "PAGEtm",
		"UNK0": "0c000800"
	},
	{
		"TYPE": "PAGE",
		"UNK0": "08000e0000000b000a00"
	},
	{
		"TYPE": "SPEAKER",
		"UNK0": "10000a00",
		"CHARACTER_ID": 12,
		"NAME": "Official"
	},
	{
		"STRINGS": [
			"\"収容員・関本爽二朗に手錠！！\""
		]
	},
	{
		"TYPE": "BR",
		"UNK0": "2c000a000103"
	},
	{
		"TYPE": "PAGEtm",
		"UNK0": "0c000800"
	},
	{
		"TYPE": "PAGE",
		"UNK0": "08000e0000000b000b00"
	},
	{
		"TYPE": "SPEAKER",
		"UNK0": "10000a00",
		"CHARACTER_ID": 12,
		"NAME": "Official"
	},
	{
		"STRINGS": [
			"\"手錠！！\""
		]
	},
	{
		"TYPE": "BR",
		"UNK0": "18000a000103"
	},
	{
		"TYPE": "PAGEtm",
		"UNK0": "0c000800"
	},
	{
		"TYPE": "EXTEND",
		"UNK0": "0800180002000000000000000000000000000000"
	},
	{
		"TYPE": "EXTEND",
		"UNK0": "1800180002000000000000000000000000000000"
	},
	{
		"TYPE": "TXTWND_OUT",
		"UNK0": "18000a001400"
	},
	{
		"TYPE": "WAIT",
		"UNK0": "0c000a001e00"
	},
	{
		"TYPE": "SE_PLAY",
		"UNK0": "0c000e00a50180800000"
	},
	{
		"TYPE": "WAIT",
		"UNK0": "10000a009600"
	},
	{
		"TYPE": "SE_PLAY",
		"UNK0": "0c000e00a50180800000"
	},
	{
		"TYPE": "WAIT",
		"UNK0": "10000a009600"
	},
	{
		"TYPE": "TXTWND_IN",
		"UNK0": "0c000a001400"
	},
	{
		"TYPE": "WAIT",
		"UNK0": "0c000a001e00"
	},
	{
		"TYPE": "PAGE",
		"UNK0": "0c000e0000000b000c00"
	},
	{
		"TYPE": "SPEAKER",
		"UNK0": "10000a00",
		"CHARACTER_ID": 12,
		"NAME": "Official"
	},
	{
		"STRINGS": [
			"\"手錠確認！\""
		]
	},
	{
		"TYPE": "BR",
		"UNK0": "1c000a000103"
	},
	{
		"TYPE": "PAGEtm",
		"UNK0": "0c000800"
	},
	{
		"TYPE": "PAGE",
		"UNK0": "08000e0000000b000d00"
	},
	{
		"TYPE": "SPEAKER",
		"UNK0": "10000a00",
		"CHARACTER_ID": 12,
		"NAME": "Official"
	},
	{
		"STRINGS": [
			"\"手錠確認！\""
		]
	},
	{
		"TYPE": "BR",
		"UNK0": "1c000a000103"
	},
	{
		"TYPE": "PAGEtm",
		"UNK0": "0c000800"
	},
	{
		"TYPE": "EXTEND",
		"UNK0": "0800180002000000000000000000000000000000"
	},
	{
		"TYPE": "MSG_WAIT",
		"UNK0": "18000a000000"
	},
	{
		"TYPE": "MSG_PLAY",
		"UNK0": "0c000e000000b3038000"
	},
	{
		"TYPE": "WAIT",
		"UNK0": "10000a005a00"
	},
	{
		"TYPE": "MSG_VOL",
		"UNK0": "0c000e0000003c000000"
	},
	{
		"TYPE": "CI_LOAD_WAIT",
		"UNK0": "10000a000000"
	},
	{
		"TYPE": "CI_BUSTUP_CENTERING",
		"UNK0": "0c0010000000080700005001"
	},
	{
		"TYPE": "CI_FADE",
		"UNK0": "10001000ffffffff14000000"
	},
	{
		"TYPE": "WAIT",
		"UNK0": "10000a001400"
	},
	{
		"TYPE": "WAIT",
		"UNK0": "0c000a002800"
	},
	{
		"TYPE": "SE_PLAY",
		"UNK0": "0c000e00a70080800000"
	},
	{
		"TYPE": "MSG_STOP",
		"UNK0": "10000a000000"
	},
	{
		"TYPE": "PAGE",
		"UNK0": "0c000e0000000b000e00"
	},
	{
		"STRINGS": [
			"手錠がしっかりかかった事を確認した彼らは、",
			"関本に正面を向かせて、私達を引き合わせた。"
		]
	},
	{
		"TYPE": "BR",
		"UNK0": "38000a000103"
	},
	{
		"TYPE": "PAGEtm",
		"UNK0": "0c000800"
	},
	{
		"TYPE": "CI_LOAD_WAIT",
		"UNK0": "08000a000100"
	},
	{
		"TYPE": "CI_BUSTUP_CENTERING",
		"UNK0": "0c001000000007070100b0fe"
	},
	{
		"TYPE": "CI_FADE",
		"UNK0": "10001000ffffffff14000100"
	},
	{
		"TYPE": "WAIT",
		"UNK0": "10000a001400"
	},
	{
		"TYPE": "PAGE",
		"UNK0": "0c000e0000000b000f00"
	},
	{
		"TYPE": "SPEAKER",
		"UNK0": "10000a00",
		"CHARACTER_ID": 7,
		"NAME": "Kuroda Kunio"
	},
	{
		"STRINGS": [
			"\"ご苦労さまです。",
			"　現時刻を以て、関本爽二朗の身柄を",
			"　Ｓ県警Ｃ村分署特殊警ら課課長、黒田邦雄が預かりました\""
		]
	},
	{
		"TYPE": "BR",
		"UNK0": "44000a000103"
	},
	{
		"TYPE": "PAGEtm",
		"UNK0": "0c000800"
	},
	{
		"TYPE": "EXTEND",
		"UNK0": "0800180002000000000000000000000000000000"
	},
	{
		"TYPE": "PAGE",
		"UNK0": "18000e0000000b001000"
	},
	{
		"STRINGS": [
			"私達は敬礼をした。",
			"彼らに手渡された関本の腰紐を私がしっかりと握る。"
		]
	},
	{
		"TYPE": "BR",
		"UNK0": "3c000a000103"
	},
	{
		"TYPE": "PAGEtm",
		"UNK0": "0c000800"
	},
	{
		"TYPE": "CI_FADE",
		"UNK0": "08001000ffffff0014000100"
	},
	{
		"TYPE": "WAIT",
		"UNK0": "10000a001400"
	},
	{
		"TYPE": "CI_FADE",
		"UNK0": "0c001000ffffff0000000100"
	},
	{
		"TYPE": "CI_LOAD",
		"UNK0": "10000c0088130100"
	},
	{
		"TYPE": "CI_FADE",
		"UNK0": "0c001000ffffff0014000000"
	},
	{
		"TYPE": "WAIT",
		"UNK0": "10000a001400"
	},
	{
		"TYPE": "CI_FADE",
		"UNK0": "0c001000ffffff0000000000"
	},
	{
		"TYPE": "CI_LOAD",
		"UNK0": "10000c00b20c0000"
	},
	{
		"TYPE": "CI_LOAD_WAIT",
		"UNK0": "0c000a000200"
	},
	{
		"TYPE": "CI_BUSTUP_CENTERING",
		"UNK0": "0c0010000000060702000000"
	},
	{
		"TYPE": "CI_FADE",
		"UNK0": "10001000ffffffff14000200"
	},
	{
		"TYPE": "WAIT",
		"UNK0": "10000a001400"
	},
	{
		"TYPE": "PAGE",
		"UNK0": "0c000e0000000b001100"
	},
	{
		"STRINGS": [
			"留置所を出ると、一定間隔に配置された署員が",
			"関本を監視する。"
		]
	},
	{
		"TYPE": "BR",
		"UNK0": "1c000a000103"
	},
	{
		"TYPE": "PAGEtm",
		"UNK0": "0c000800"
	},
	{
		"TYPE": "PAGE",
		"UNK0": "08000e0000000b001200"
	},
	{
		"STRINGS": [
			"不足の事態に備えて、厳重な警戒を行っているのだ。",
			"なにせ、オブザーバーとして公判途中で殺人犯を",
			"連れてきたのは前代未聞の事だから。"
		]
	},
	{
		"TYPE": "BR",
		"UNK0": "30000a000103"
	},
	{
		"TYPE": "PAGEtm",
		"UNK0": "0c000800"
	},
	{
		"TYPE": "PAGE",
		"UNK0": "08000e0000000b001300"
	},
	{
		"TYPE": "SPEAKER",
		"UNK0": "10000a00",
		"CHARACTER_ID": 6,
		"NAME": "Houjou Saki"
	},
	{
		"STRINGS": [
			"\"行きましょう\""
		]
	},
	{
		"TYPE": "BR",
		"UNK0": "1c000a000103"
	},
	{
		"TYPE": "PAGEtm",
		"UNK0": "0c000800"
	},
	{
		"TYPE": "EXTEND",
		"UNK0": "0800180002000000000000000000000000000000"
	},
	{
		"TYPE": "PAGE",
		"UNK0": "18000e0000000b001400"
	},
	{
		"STRINGS": [
			"私は、関本の耳だけに聞こえるように",
			"静かに移動開始を促した。"
		]
	},
	{
		"TYPE": "BR",
		"UNK0": "24000a000103"
	},
	{
		"TYPE": "PAGEtm",
		"UNK0": "0c000800"
	},
	{
		"TYPE": "EXTEND",
		"UNK0": "0800180002000000000000000000000000000000"
	},
	{
		"TYPE": "TXTWND_OUT",
		"UNK0": "18000a001400"
	},
	{
		"TYPE": "WAIT",
		"UNK0": "0c000a001e00"
	},
	{
		"TYPE": "SE_PLAY",
		"UNK0": "0c000e00a80080800000"
	},
	{
		"TYPE": "LOOPS_VOL",
		"UNK0": "10000e0000003c000000"
	},
	{
		"TYPE": "SCR_FADE",
		"UNK0": "10001000000000803c000000"
	},
	{
		"TYPE": "WAIT",
		"UNK0": "10000a003c00"
	},
	{
		"TYPE": "LOOPS_VOL",
		"UNK0": "0c000e00000000000000"
	},
	{
		"TYPE": "LOOPS_STOP",
		"UNK0": "10000a000000"
	},
	{
		"TYPE": "LOOPS_READY",
		"UNK0": "0c000c0026020000"
	},
	{
		"TYPE": "BG_FADE",
		"UNK0": "0c0010000000000000000100"
	},
	{
		"TYPE": "BG_MOVE",
		"UNK0": "1000120000000000d00700000100"
	},
	{
		"TYPE": "BG_SET_ADJUST_Z",
		"UNK0": "14000c0001000100"
	},
	{
		"TYPE": "BG_LOAD",
		"UNK0": "0c000c0058750100"
	},
	{
		"TYPE": "BG_WAIT",
		"UNK0": "0c000a000200"
	},
	{
		"TYPE": "BG_SET_ADJUST_Z",
		"UNK0": "0c000c0002000200"
	},
	{
		"TYPE": "BG_FADE",
		"UNK0": "0c001000ffffffff00000200"
	},
	{
		"TYPE": "WAIT",
		"UNK0": "10000a002c01"
	},
	{
		"TYPE": "CI_FADE",
		"UNK0": "0c001000ffffff0014000200"
	},
	{
		"TYPE": "WAIT",
		"UNK0": "10000a001400"
	},
	{
		"TYPE": "CI_FADE",
		"UNK0": "0c001000ffffff0000000200"
	},
	{
		"TYPE": "CI_LOAD",
		"UNK0": "10000c009c130200"
	},
	{
		"TYPE": "SE_PLAY",
		"UNK0": "0c000e00450180800000"
	},
	{
		"TYPE": "SCR_FADE",
		"UNK0": "10001000000000003c000000"
	},
	{
		"TYPE": "WAIT",
		"UNK0": "10000a003c00"
	},
	{
		"TYPE": "WAIT",
		"UNK0": "0c000a003c00"
	},
	{
		"TYPE": "TXTWND_IN",
		"UNK0": "0c000a001400"
	},
	{
		"TYPE": "WAIT",
		"UNK0": "0c000a001e00"
	},
	{
		"TYPE": "PAGE",
		"UNK0": "0c000e0000000b001500"
	},
	{
		"STRINGS": [
			"一階にあがると、蛍光灯の白い光が",
			"私達全員を包み込んで眩しい。"
		]
	},
	{
		"TYPE": "BR",
		"UNK0": "28000a000103"
	},
	{
		"TYPE": "PAGEtm",
		"UNK0": "0c000800"
	},
	{
		"TYPE": "PAGE",
		"UNK0": "08000e0000000b001600"
	},
	{
		"STRINGS": [
			"警察署の一階も、いつもと雰囲気がまったく違った。",
			"いつもはまばらに見受けられる一般人がまったくいない。",
			"おそらく関本の護送のために人払いをしたのだ。"
		]
	},
	{
		"TYPE": "BR",
		"UNK0": "38000a000103"
	},
	{
		"TYPE": "PAGEtm",
		"UNK0": "0c000800"
	},
	{
		"TYPE": "PAGE",
		"UNK0": "08000e0000000b001700"
	},
	{
		"STRINGS": [
			"順番を待つ間に暇を潰すテレビも消されている。",
			"その代わり、やはり署員たちが一定間隔で立って、",
			"私達の護送の様子を注視していた。"
		]
	},
	{
		"TYPE": "BR",
		"UNK0": "2c000a000103"
	},
	{
		"TYPE": "PAGEtm",
		"UNK0": "0c000800"
	},
	{
		"TYPE": "PAGE",
		"UNK0": "08000e0000000b001800"
	},
	{
		"STRINGS": [
			"私達は、その中心に立っていた。",
			"私はその様子があるものに似ていると感じた。",
			"それは——"
		]
	},
	{
		"TYPE": "BR",
		"UNK0": "18000a000103"
	},
	{
		"TYPE": "PAGEtm",
		"UNK0": "0c000800"
	},
	{
		"TYPE": "PAGE",
		"UNK0": "08000e0000000b001900"
	},
	{
		"TYPE": "SPEAKER",
		"UNK0": "10000a00",
		"CHARACTER_ID": 6,
		"NAME": "Houjou Saki"
	},
	{
		"STRINGS": [
			"\"……ハーメルンの笛吹き男\""
		]
	},
	{
		"TYPE": "DATABASE",
		"UNK0": "28001600d713000a7c917ea47c7e7c747c6c"
	},
	{
		"TYPE": "BR",
		"UNK0": "18000a000103"
	},
	{
		"TYPE": "PAGEtm",
		"UNK0": "0c000800"
	},
	{
		"TYPE": "EXTEND",
		"UNK0": "0800180002000000000000000000000000000000"
	},
	{
		"TYPE": "PAGE",
		"UNK0": "18000e0000000b001a00"
	},
	{
		"STRINGS": [
			"思わず小さな声で呟いてしまい、",
			"黒田課長に咳払いで注意された。"
		]
	},
	{
		"TYPE": "BR",
		"UNK0": "2c000a000103"
	},
	{
		"TYPE": "PAGEtm",
		"UNK0": "0c000800"
	},
	{
		"TYPE": "PAGE",
		"UNK0": "08000e0000000b001b00"
	},
	{
		"STRINGS": [
			"まるでこれはハーメルンの笛吹き男。"
		]
	},
	{
		"TYPE": "BR",
		"UNK0": "34000a000103"
	},
	{
		"TYPE": "PAGEtm",
		"UNK0": "0c000800"
	},
	{
		"TYPE": "PAGE",
		"UNK0": "08000e0000000b001c00"
	},
	{
		"STRINGS": [
			"さしずめ私達はマグス。"
		]
	},
	{
		"TYPE": "BR",
		"UNK0": "28000a000103"
	},
	{
		"TYPE": "PAGEtm",
		"UNK0": "0c000800"
	},
	{
		"TYPE": "PAGE",
		"UNK0": "08000e0000000b001d00"
	},
	{
		"STRINGS": [
			"連れ出される関本はムース。"
		]
	},
	{
		"TYPE": "BR",
		"UNK0": "2c000a000103"
	},
	{
		"TYPE": "PAGEtm",
		"UNK0": "0c000800"
	},
	{
		"TYPE": "PAGE",
		"UNK0": "08000e0000000b001e00"
	},
	{
		"STRINGS": [
			"そんな私達を見つめるのはハーメルンの民衆達。"
		]
	},
	{
		"TYPE": "BR",
		"UNK0": "3c000a000103"
	},
	{
		"TYPE": "PAGEtm",
		"UNK0": "0c000800"
	},
	{
		"TYPE": "PAGE",
		"UNK0": "08000e0000000b001f00"
	},
	{
		"STRINGS": [
			"おそらく、署員達にとって関本は、家々を荒らす",
			"鼠だったに違いない。"
		]
	},
	{
		"TYPE": "BR",
		"UNK0": "20000a000103"
	},
	{
		"TYPE": "PAGEtm",
		"UNK0": "0c000800"
	},
	{
		"TYPE": "PAGE",
		"UNK0": "08000e0000000b002000"
	},
	{
		"STRINGS": [
			"事件捜査のペースをかき乱されていた彼らは",
			"さぞかし、ほっ、としている事だろう。"
		]
	},
	{
		"TYPE": "BR",
		"UNK0": "30000a000103"
	},
	{
		"TYPE": "PAGEtm",
		"UNK0": "0c000800"
	},
	{
		"TYPE": "PAGE",
		"UNK0": "08000e0000000b002100"
	},
	{
		"STRINGS": [
			"だが、本当に関本はそうなのか。"
		]
	},
	{
		"TYPE": "BR",
		"UNK0": "30000a000103"
	},
	{
		"TYPE": "PAGEtm",
		"UNK0": "0c000800"
	},
	{
		"TYPE": "PAGE",
		"UNK0": "08000e0000000b002200"
	},
	{
		"STRINGS": [
			"彼を街から追い出したからといって、",
			"決して本当の災厄––ブラインドマンを炙り出してはいない。"
		]
	},
	{
		"TYPE": "BR",
		"UNK0": "44000a000103"
	},
	{
		"TYPE": "PAGEtm",
		"UNK0": "0c000800"
	},
	{
		"TYPE": "PAGE",
		"UNK0": "08000e0000000b002300"
	},
	{
		"STRINGS": [
			"分署のロビー入り口には、署長が待ち構えていた。",
			"私と黒田課長は、敬礼をする。"
		]
	},
	{
		"TYPE": "BR",
		"UNK0": "28000a000103"
	},
	{
		"TYPE": "PAGEtm",
		"UNK0": "0c000800"
	},
	{
		"TYPE": "SE_PLAY",
		"UNK0": "08000e00960380800000"
	},
	{
		"TYPE": "WAIT",
		"UNK0": "10000a000a00"
	},
	{
		"TYPE": "SE_PLAY",
		"UNK0": "0c000e00ba0396960000"
	},
	{
		"TYPE": "CI_LOAD_WAIT",
		"UNK0": "10000a000300"
	},
	{
		"TYPE": "CI_BUSTUP_CENTERING",
		"UNK0": "0c0010000000050703000000"
	},
	{
		"TYPE": "CI_FADE",
		"UNK0": "10001000ffffffff14000300"
	},
	{
		"TYPE": "WAIT",
		"UNK0": "10000a001400"
	},
	{
		"TYPE": "WAIT",
		"UNK0": "0c000a003c00"
	},
	{
		"TYPE": "PAGE",
		"UNK0": "0c000e0000000b002400"
	},
	{
		"TYPE": "SPEAKER",
		"UNK0": "10000a00",
		"CHARACTER_ID": 7,
		"NAME": "Kuroda Kunio"
	},
	{
		"STRINGS": [
			"\"署長。私達、特殊警ら課員２名、",
			"　黒田邦雄と北條紗希は、現時点を以て",
			"　参考人・関本爽二朗の東京拘置所送還を開始いたします\""
		]
	},
	{
		"TYPE": "BR",
		"UNK0": "44000a000103"
	},
	{
		"TYPE": "PAGEtm",
		"UNK0": "0c000800"
	},
	{
		"TYPE": "EXTEND",
		"UNK0": "0800180002000000000000000000000000000000"
	},
	{
		"TYPE": "PAGE",
		"UNK0": "18000e0000000b002500"
	},
	{
		"TYPE": "SPEAKER",
		"UNK0": "10000a00",
		"CHARACTER_ID": 42,
		"NAME": "Police Chief"
	},
	{
		"STRINGS": [
			"\"職責を重々認識し、確実、安全な職務遂行を",
			"　望みます。よろしくお願い致します\""
		]
	},
	{
		"TYPE": "BR",
		"UNK0": "30000a000103"
	},
	{
		"TYPE": "PAGEtm",
		"UNK0": "0c000800"
	},
	{
		"TYPE": "EXTEND",
		"UNK0": "0800180002000000000000000000000000000000"
	},
	{
		"TYPE": "PAGE",
		"UNK0": "18000e0000000b002600"
	},
	{
		"TYPE": "SPEAKER",
		"UNK0": "10000a00",
		"CHARACTER_ID": 7,
		"NAME": "Kuroda Kunio"
	},
	{
		"STRINGS": [
			"\"了解！\""
		]
	},
	{
		"TYPE": "BR",
		"UNK0": "18000a000103"
	},
	{
		"TYPE": "PAGEtm",
		"UNK0": "0c000800"
	},
	{
		"TYPE": "EXTEND",
		"UNK0": "0800180002000000000000000000000000000000"
	},
	{
		"TYPE": "EXTEND",
		"UNK0": "1800180002000000000000000000000000000000"
	},
	{
		"TYPE": "TXTWND_OUT",
		"UNK0": "18000a001400"
	},
	{
		"TYPE": "WAIT",
		"UNK0": "0c000a001e00"
	},
	{
		"TYPE": "SCR_FADE",
		"UNK0": "0c001000000000803c000000"
	},
	{
		"TYPE": "WAIT",
		"UNK0": "10000a003c00"
	},
	{
		"TYPE": "CI_FADE",
		"UNK0": "0c001000ffffff0014000300"
	},
	{
		"TYPE": "WAIT",
		"UNK0": "10000a001400"
	},
	{
		"TYPE": "CI_FADE",
		"UNK0": "0c001000ffffff0000000300"
	},
	{
		"TYPE": "CI_LOAD",
		"UNK0": "10000c00b20c0300"
	},
	{
		"TYPE": "BG_FADE",
		"UNK0": "0c0010000000000000000200"
	},
	{
		"TYPE": "BG_MOVE",
		"UNK0": "1000120000000000d00700000200"
	},
	{
		"TYPE": "BG_SET_ADJUST_Z",
		"UNK0": "14000c0002000200"
	},
	{
		"TYPE": "BG_LOAD",
		"UNK0": "0c000c0058750200"
	},
	{
		"TYPE": "BG_WAIT",
		"UNK0": "0c000a000400"
	},
	{
		"TYPE": "BG_SET_ADJUST_Z",
		"UNK0": "0c000c0004000400"
	},
	{
		"TYPE": "BG_FADE",
		"UNK0": "0c001000ffffffff00000400"
	},
	{
		"TYPE": "SCR_FADE",
		"UNK0": "10001000000000003c000000"
	},
	{
		"TYPE": "WAIT",
		"UNK0": "10000a003c00"
	},
	{
		"TYPE": "SE_PLAY",
		"UNK0": "0c000e00960380800000"
	},
	{
		"TYPE": "WAIT",
		"UNK0": "10000a000a00"
	},
	{
		"TYPE": "SE_PLAY",
		"UNK0": "0c000e00ba0396960000"
	},
	{
		"TYPE": "TXTWND_IN",
		"UNK0": "10000a001400"
	},
	{
		"TYPE": "WAIT",
		"UNK0": "0c000a001e00"
	},
	{
		"TYPE": "PAGE",
		"UNK0": "0c000e0000000b002700"
	},
	{
		"STRINGS": [
			"私達は再び署長に敬礼を行った。",
			"そして、入り口正面には、エンジンをかけたままの",
			"ワンボックスタイプのライトバンが待機していた。"
		]
	},
	{
		"TYPE": "BR",
		"UNK0": "3c000a000103"
	},
	{
		"TYPE": "PAGEtm",
		"UNK0": "0c000800"
	},
	{
		"TYPE": "LOOPS_WAIT",
		"UNK0": "08000a000000"
	},
	{
		"TYPE": "LOOPS_PLAY",
		"UNK0": "0c0010002602000000000000"
	},
	{
		"TYPE": "LOOPS_VOL",
		"UNK0": "10000e00000000000000"
	},
	{
		"TYPE": "LOOPS_VOL",
		"UNK0": "10000e0078003c000000"
	},
	{
		"TYPE": "WAIT",
		"UNK0": "10000a003c00"
	},
	{
		"TYPE": "LOOPS_VOL",
		"UNK0": "0c000e00000000000100"
	},
	{
		"TYPE": "LOOPS_STOP",
		"UNK0": "10000a000100"
	},
	{
		"TYPE": "LOOPS_READY",
		"UNK0": "0c000c00f3020100"
	},
	{
		"TYPE": "PAGE",
		"UNK0": "0c000e0000000b002800"
	},
	{
		"STRINGS": [
			"そのワンボックスカーは、車両後部の窓が白く塗られており、",
			"中の様子をうかがう事ができない。"
		]
	},
	{
		"TYPE": "BR",
		"UNK0": "2c000a000103"
	},
	{
		"TYPE": "PAGEtm",
		"UNK0": "0c000800"
	},
	{
		"TYPE": "SE_PLAY",
		"UNK0": "08000e00300180800000"
	},
	{
		"TYPE": "WAIT",
		"UNK0": "10000a003c00"
	},
	{
		"TYPE": "PAGE",
		"UNK0": "0c000e0000000b002900"
	},
	{
		"STRINGS": [
			"その扉を開ける。",
			"すると素っ気ない座席シートが私達を待ち受けていた。"
		]
	},
	{
		"TYPE": "BR",
		"UNK0": "40000a000103"
	},
	{
		"TYPE": "PAGEtm",
		"UNK0": "0c000800"
	},
	{
		"TYPE": "PAGE",
		"UNK0": "08000e0000000b002a00"
	},
	{
		"TYPE": "SPEAKER",
		"UNK0": "10000a00",
		"CHARACTER_ID": 6,
		"NAME": "Houjou Saki"
	},
	{
		"STRINGS": [
			"\"参考人、乗車します\""
		]
	},
	{
		"TYPE": "BR",
		"UNK0": "24000a000103"
	},
	{
		"TYPE": "PAGEtm",
		"UNK0": "0c000800"
	},
	{
		"TYPE": "EXTEND",
		"UNK0": "0800180002000000000000000000000000000000"
	},
	{
		"TYPE": "PAGE",
		"UNK0": "18000e0000000b002b00"
	},
	{
		"TYPE": "SPEAKER",
		"UNK0": "10000a00",
		"CHARACTER_ID": 12,
		"NAME": "Official"
	},
	{
		"STRINGS": [
			"\"乗車！！\""
		]
	},
	{
		"TYPE": "BR",
		"UNK0": "18000a000103"
	},
	{
		"TYPE": "PAGEtm",
		"UNK0": "0c000800"
	},
	{
		"TYPE": "EXTEND",
		"UNK0": "0800180002000000000000000000000000000000"
	},
	{
		"TYPE": "PAGE",
		"UNK0": "18000e0000000b002c00"
	},
	{
		"TYPE": "SPEAKER",
		"UNK0": "10000a00",
		"CHARACTER_ID": 6,
		"NAME": "Houjou Saki"
	},
	{
		"STRINGS": [
			"\"……乗って下さい\""
		]
	},
	{
		"TYPE": "BR",
		"UNK0": "20000a000103"
	},
	{
		"TYPE": "PAGEtm",
		"UNK0": "0c000800"
	},
	{
		"TYPE": "EXTEND",
		"UNK0": "0800180002000000000000000000000000000000"
	},
	{
		"TYPE": "EXTEND",
		"UNK0": "1800180002000000000000000000000000000000"
	},
	{
		"TYPE": "TXTWND_OUT",
		"UNK0": "18000a001400"
	},
	{
		"TYPE": "WAIT",
		"UNK0": "0c000a001e00"
	},
	{
		"TYPE": "MSG_STOP",
		"UNK0": "0c000a000000"
	},
	{
		"TYPE": "MSG_READY",
		"UNK0": "0c000c000000a003"
	},
	{
		"TYPE": "MSG_WAIT",
		"UNK0": "0c000a000000"
	},
	{
		"TYPE": "MSG_PLAY",
		"UNK0": "0c000e000000a0038000"
	},
	{
		"TYPE": "WAIT",
		"UNK0": "10000a003c00"
	},
	{
		"TYPE": "MSG_VOL",
		"UNK0": "0c000e0000003c000000"
	},
	{
		"TYPE": "WAIT",
		"UNK0": "10000a005000"
	},
	{
		"TYPE": "MSG_STOP",
		"UNK0": "0c000a000100"
	},
	{
		"TYPE": "MSG_READY",
		"UNK0": "0c000c000100a103"
	},
	{
		"TYPE": "MSG_WAIT",
		"UNK0": "0c000a000100"
	},
	{
		"TYPE": "MSG_PLAY",
		"UNK0": "0c000e000100a1038000"
	},
	{
		"TYPE": "WAIT",
		"UNK0": "10000a003c00"
	},
	{
		"TYPE": "MSG_VOL",
		"UNK0": "0c000e0001003c000000"
	},
	{
		"TYPE": "TXTWND_IN",
		"UNK0": "10000a001400"
	},
	{
		"TYPE": "WAIT",
		"UNK0": "0c000a001e00"
	},
	{
		"TYPE": "PAGE",
		"UNK0": "0c000e0000000b002d00"
	},
	{
		"STRINGS": [
			"私は関本に車内乗車を促した。",
			"私達が乗り込むと、即座に扉が閉められた。"
		]
	},
	{
		"TYPE": "BR",
		"UNK0": "34000a000103"
	},
	{
		"TYPE": "PAGEtm",
		"UNK0": "0c000800"
	},
	{
		"TYPE": "EXTEND",
		"UNK0": "0800180002000000000000000000000000000000"
	},
	{
		"TYPE": "TXTWND_OUT",
		"UNK0": "18000a001400"
	},
	{
		"TYPE": "WAIT",
		"UNK0": "0c000a001e00"
	},
	{
		"TYPE": "SE_PLAY",
		"UNK0": "0c000e00310180800000"
	},
	{
		"TYPE": "SCR_FADE",
		"UNK0": "10001000000000803c000000"
	},
	{
		"TYPE": "WAIT",
		"UNK0": "10000a003c00"
	},
	{
		"TYPE": "MSG_STOP",
		"UNK0": "0c000a000000"
	},
	{
		"TYPE": "MSG_STOP",
		"UNK0": "0c000a000100"
	},
	{
		"TYPE": "BG_FADE",
		"UNK0": "0c0010000000000000000400"
	},
	{
		"TYPE": "BG_MOVE",
		"UNK0": "1000120000000000d00700000400"
	},
	{
		"TYPE": "BG_SET_ADJUST_Z",
		"UNK0": "14000c0004000400"
	},
	{
		"TYPE": "BG_WAIT",
		"UNK0": "0c000a000300"
	},
	{
		"TYPE": "BG_SET_ADJUST_Z",
		"UNK0": "0c000c0003000300"
	},
	{
		"TYPE": "BG_FADE",
		"UNK0": "0c001000ffffffff00000300"
	},
	{
		"TYPE": "SCR_FADE",
		"UNK0": "10001000000000003c000000"
	},
	{
		"TYPE": "WAIT",
		"UNK0": "10000a003c00"
	},
	{
		"TYPE": "TXTWND_IN",
		"UNK0": "0c000a001400"
	},
	{
		"TYPE": "WAIT",
		"UNK0": "0c000a001e00"
	},
	{
		"TYPE": "PAGE",
		"UNK0": "0c000e0000000b002e00"
	},
	{
		"STRINGS": [
			"この車は外見は一般的な車両に見えるが、",
			"内実は警察車両用のために改装された特殊車両だ。"
		]
	},
	{
		"TYPE": "BR",
		"UNK0": "3c000a000103"
	},
	{
		"TYPE": "PAGEtm",
		"UNK0": "0c000800"
	},
	{
		"TYPE": "PAGE",
		"UNK0": "08000e0000000b002f00"
	},
	{
		"STRINGS": [
			"一度、後部座席に乗車してしまうと、",
			"ドライバーシートの操作なしでは外に出る事はできない。"
		]
	},
	{
		"TYPE": "BR",
		"UNK0": "40000a000103"
	},
	{
		"TYPE": "PAGEtm",
		"UNK0": "0c000800"
	},
	{
		"TYPE": "SE_PLAY",
		"UNK0": "08000e00320180800000"
	},
	{
		"TYPE": "WAIT",
		"UNK0": "10000a003c00"
	},
	{
		"TYPE": "SE_PLAY",
		"UNK0": "0c000e00330180800000"
	},
	{
		"TYPE": "WAIT",
		"UNK0": "10000a001e00"
	},
	{
		"TYPE": "PAGE",
		"UNK0": "0c000e0000000b003000"
	},
	{
		"STRINGS": [
			"黒田課長も助手席に乗り込んだ。"
		]
	},
	{
		"TYPE": "BR",
		"UNK0": "30000a000103"
	},
	{
		"TYPE": "PAGEtm",
		"UNK0": "0c000800"
	},
	{
		"TYPE": "PAGE",
		"UNK0": "08000e0000000b003100"
	},
	{
		"STRINGS": [
			"本来ならば、関本を中央で挟むように座るのだが、",
			"あくまで今回は参考人の護送名目である事、",
			"またこの車種は入り口がひとつのため私だけが同伴する。"
		]
	},
	{
		"TYPE": "BR",
		"UNK0": "40000a000103"
	},
	{
		"TYPE": "PAGEtm",
		"UNK0": "0c000800"
	},
	{
		"TYPE": "CI_LOAD_WAIT",
		"UNK0": "08000a000100"
	},
	{
		"TYPE": "CI_BUSTUP_CENTERING",
		"UNK0": "0c0010000000070701000000"
	},
	{
		"TYPE": "CI_FADE",
		"UNK0": "10001000ffffffff14000100"
	},
	{
		"TYPE": "WAIT",
		"UNK0": "10000a001400"
	},
	{
		"TYPE": "PAGE",
		"UNK0": "0c000e0000000b003200"
	},
	{
		"TYPE": "SPEAKER",
		"UNK0": "10000a00",
		"CHARACTER_ID": 7,
		"NAME": "Kuroda Kunio"
	},
	{
		"STRINGS": [
			"\"後ろはもう準備はいいかい\""
		]
	},
	{
		"TYPE": "BR",
		"UNK0": "28000a000103"
	},
	{
		"TYPE": "PAGEtm",
		"UNK0": "0c000800"
	},
	{
		"TYPE": "EXTEND",
		"UNK0": "0800180002000000000000000000000000000000"
	},
	{
		"TYPE": "PAGE",
		"UNK0": "18000e0000000b003300"
	},
	{
		"TYPE": "SPEAKER",
		"UNK0": "10000a00",
		"CHARACTER_ID": 6,
		"NAME": "Houjou Saki"
	},
	{
		"STRINGS": [
			"\"はい。お願いします\""
		]
	},
	{
		"TYPE": "BR",
		"UNK0": "24000a000103"
	},
	{
		"TYPE": "PAGEtm",
		"UNK0": "0c000800"
	},
	{
		"TYPE": "EXTEND",
		"UNK0": "0800180002000000000000000000000000000000"
	},
	{
		"TYPE": "CI_FADE",
		"UNK0": "18001000ffffff0014000100"
	},
	{
		"TYPE": "WAIT",
		"UNK0": "10000a001400"
	},
	{
		"TYPE": "CI_FADE",
		"UNK0": "0c001000ffffff0000000100"
	},
	{
		"TYPE": "CI_LOAD",
		"UNK0": "10000c00800c0100"
	},
	{
		"TYPE": "PAGE",
		"UNK0": "0c000e0000000b003400"
	},
	{
		"STRINGS": [
			"前部座席と後部座席を仕切る金網越しに黒田課長が",
			"確認してきた。"
		]
	},
	{
		"TYPE": "BR",
		"UNK0": "1c000a000103"
	},
	{
		"TYPE": "PAGEtm",
		"UNK0": "0c000800"
	},
	{
		"TYPE": "PAGE",
		"UNK0": "08000e0000000b003500"
	},
	{
		"STRINGS": [
			"私の返事を確認した黒田課長は",
			"運転席に座るドライバーに発車をお願いした。"
		]
	},
	{
		"TYPE": "BR",
		"UNK0": "38000a000103"
	},
	{
		"TYPE": "PAGEtm",
		"UNK0": "0c000800"
	},
	{
		"TYPE": "PAGE",
		"UNK0": "08000e0000000b003600"
	},
	{
		"STRINGS": [
			"ドライバーは本来ならば、風守さんの役目だ。",
			"だが、彼がいないので警察庁から要員を手配していた。"
		]
	},
	{
		"TYPE": "BR",
		"UNK0": "40000a000103"
	},
	{
		"TYPE": "PAGEtm",
		"UNK0": "0c000800"
	},
	{
		"TYPE": "CI_LOAD_WAIT",
		"UNK0": "08000a000200"
	},
	{
		"TYPE": "CI_BUSTUP_CENTERING",
		"UNK0": "0c0010000000060702000000"
	},
	{
		"TYPE": "CI_FADE",
		"UNK0": "10001000ffffffff14000200"
	},
	{
		"TYPE": "WAIT",
		"UNK0": "10000a001400"
	},
	{
		"TYPE": "PAGE",
		"UNK0": "0c000e0000000b003700"
	},
	{
		"TYPE": "SPEAKER",
		"UNK0": "10000a00",
		"CHARACTER_ID": 7,
		"NAME": "Kuroda Kunio"
	},
	{
		"STRINGS": [
			"\"では、行きましょう\""
		]
	},
	{
		"TYPE": "BR",
		"UNK0": "24000a000103"
	},
	{
		"TYPE": "PAGEtm",
		"UNK0": "0c000800"
	},
	{
		"TYPE": "EXTEND",
		"UNK0": "0800180002000000000000000000000000000000"
	},
	{
		"TYPE": "CI_FADE",
		"UNK0": "18001000ffffff0014000200"
	},
	{
		"TYPE": "WAIT",
		"UNK0": "10000a001400"
	},
	{
		"TYPE": "CI_FADE",
		"UNK0": "0c001000ffffff0000000200"
	},
	{
		"TYPE": "CI_LOAD",
		"UNK0": "10000c00940c0200"
	},
	{
		"TYPE": "SE_PLAY",
		"UNK0": "0c000e00420246460000"
	},
	{
		"TYPE": "LOOPS_VOL",
		"UNK0": "10000e0000001e000000"
	},
	{
		"TYPE": "SE_PLAY",
		"UNK0": "10000e002d0280800000"
	},
	{
		"TYPE": "WAIT",
		"UNK0": "10000a001e00"
	},
	{
		"TYPE": "LOOPS_VOL",
		"UNK0": "0c000e00000000000000"
	},
	{
		"TYPE": "LOOPS_STOP",
		"UNK0": "10000a000000"
	},
	{
		"TYPE": "LOOPS_READY",
		"UNK0": "0c000c002b020000"
	},
	{
		"TYPE": "WAIT",
		"UNK0": "0c000a000500"
	},
	{
		"TYPE": "LOOPS_WAIT",
		"UNK0": "0c000a000000"
	},
	{
		"TYPE": "LOOPS_PLAY",
		"UNK0": "0c0010002b02000000000000"
	},
	{
		"TYPE": "LOOPS_VOL",
		"UNK0": "10000e00800000000000"
	},
	{
		"TYPE": "PAGE",
		"UNK0": "10000e0000000b003800"
	},
	{
		"STRINGS": [
			"黒田課長がそう短く告げると、",
			"車は静かに発車した。"
		]
	},
	{
		"TYPE": "BR",
		"UNK0": "20000a000103"
	},
	{
		"TYPE": "PAGEtm",
		"UNK0": "0c000800"
	},
	{
		"TYPE": "EXTEND",
		"UNK0": "0800180002000000000000000000000000000000"
	},
	{
		"TYPE": "TXTWND_OUT",
		"UNK0": "18000a001400"
	},
	{
		"TYPE": "WAIT",
		"UNK0": "0c000a001e00"
	},
	{
		"TYPE": "CALL_DEMO",
		"UNK0": "0c001c00a41f000000000000000000000000000000000000"
	},
	{
		"TYPE": "WAIT_DEMO_ALL",
		"UNK0": "1c000800"
	},
	{
		"TYPE": "LOOPS_VOL",
		"UNK0": "08000e0000003c000000"
	},
	{
		"TYPE": "WAIT",
		"UNK0": "10000a003c00"
	},
	{
		"TYPE": "LOOPS_VOL",
		"UNK0": "0c000e00000000000000"
	},
	{
		"TYPE": "LOOPS_STOP",
		"UNK0": "10000a000000"
	},
	{
		"TYPE": "LOOPS_READY",
		"UNK0": "0c000c002b020000"
	},
	{
		"TYPE": "WAIT",
		"UNK0": "0c000a006400"
	},
	{
		"TYPE": "LOOPS_WAIT",
		"UNK0": "0c000a000000"
	},
	{
		"TYPE": "LOOPS_PLAY",
		"UNK0": "0c0010002b02000000000000"
	},
	{
		"TYPE": "LOOPS_VOL",
		"UNK0": "10000e00000000000000"
	},
	{
		"TYPE": "LOOPS_VOL",
		"UNK0": "10000e003c003c000000"
	},
	{
		"TYPE": "WAIT",
		"UNK0": "10000a003c00"
	},
	{
		"TYPE": "CALL_DEMO",
		"UNK0": "0c001c00a51f000000000000000000000000000000000000"
	},
	{
		"TYPE": "WAIT_DEMO_ALL",
		"UNK0": "1c000800"
	},
	{
		"TYPE": "WAIT",
		"UNK0": "08000a003c00"
	},
	{
		"TYPE": "BGM_PLAY",
		"UNK0": "0c000c0009000100"
	},
	{
		"TYPE": "BGM_VOL",
		"UNK0": "0c000c0000008000"
	},
	{
		"TYPE": "WAIT",
		"UNK0": "0c000a005a00"
	},
	{
		"TYPE": "TXTWND_IN",
		"UNK0": "0c000a001400"
	},
	{
		"TYPE": "WAIT",
		"UNK0": "0c000a001e00"
	},
	{
		"TYPE": "PAGE",
		"UNK0": "0c000e0000000b003900"
	},
	{
		"STRINGS": [
			"警察署を出て、村の中心部を抜けると",
			"すぐに狭い山道に出た。"
		]
	},
	{
		"TYPE": "BR",
		"UNK0": "24000a000103"
	},
	{
		"TYPE": "PAGEtm",
		"UNK0": "0c000800"
	},
	{
		"TYPE": "PAGE",
		"UNK0": "08000e0000000b003a00"
	},
	{
		"STRINGS": [
			"しばらくは殺風景な道が続く。",
			"後部座席にいる私と関本は外の様子を窺う事ができない。",
			"ただ左右に身体を揺らしていた。"
		]
	},
	{
		"TYPE": "BR",
		"UNK0": "2c000a000103"
	},
	{
		"TYPE": "PAGEtm",
		"UNK0": "0c000800"
	},
	{
		"TYPE": "PAGE",
		"UNK0": "08000e0000000b003b00"
	},
	{
		"STRINGS": [
			"私は黙って前を見つめていた。",
			"時折、関本に注意を払ったが、彼もまた姿勢を正したまま",
			"黙って前を向いていた。"
		]
	},
	{
		"TYPE": "BR",
		"UNK0": "24000a000103"
	},
	{
		"TYPE": "PAGEtm",
		"UNK0": "0c000800"
	},
	{
		"TYPE": "PAGE",
		"UNK0": "08000e0000000b003c00"
	},
	{
		"STRINGS": [
			"フロントガラスから見える景色は、ただの暗闇だ。",
			"ライトの光は、ほんのすぐ先を照らすばかりで",
			"視界はあまり良好とは言えない。"
		]
	},
	{
		"TYPE": "BR",
		"UNK0": "2c000a000103"
	},
	{
		"TYPE": "PAGEtm",
		"UNK0": "0c000800"
	},
	{
		"TYPE": "PAGE",
		"UNK0": "08000e0000000b003d00"
	},
	{
		"STRINGS": [
			"まるでそれは、私達の今後を物語っているようで、",
			"不安をかき立てるかのようだった。"
		]
	},
	{
		"TYPE": "BR",
		"UNK0": "2c000a000103"
	},
	{
		"TYPE": "PAGEtm",
		"UNK0": "0c000800"
	},
	{
		"TYPE": "PAGE",
		"UNK0": "08000e0000000b003e00"
	},
	{
		"STRINGS": [
			"このまましばらく、こんな景色が続く。",
			"麓の市街地に出て、高速道路に乗れば一時間ほどで都内だ。"
		]
	},
	{
		"TYPE": "BR",
		"UNK0": "44000a000103"
	},
	{
		"TYPE": "PAGEtm",
		"UNK0": "0c000800"
	},
	{
		"TYPE": "PAGE",
		"UNK0": "08000e0000000b003f00"
	},
	{
		"STRINGS": [
			"つまり、関本とは、もう少しで二度と会わない。",
			"そう気付いた時、私はもう一度、彼の様子に気を払った。"
		]
	},
	{
		"TYPE": "BR",
		"UNK0": "40000a000103"
	},
	{
		"TYPE": "PAGEtm",
		"UNK0": "0c000800"
	},
	{
		"TYPE": "CI_LOAD_WAIT",
		"UNK0": "08000a000000"
	},
	{
		"TYPE": "CI_BUSTUP_CENTERING",
		"UNK0": "0c0010000000080700000000"
	},
	{
		"TYPE": "CI_FADE",
		"UNK0": "10001000ffffffff14000000"
	},
	{
		"TYPE": "WAIT",
		"UNK0": "10000a001400"
	},
	{
		"TYPE": "PAGE",
		"UNK0": "0c000e0000000b004000"
	},
	{
		"TYPE": "SPEAKER",
		"UNK0": "10000a00",
		"CHARACTER_ID": 3,
		"NAME": "Sekimoto Soujirou"
	},
	{
		"STRINGS": [
			"\"こういうシチュエーションの時、",
			"　私は喋る事を許されているのかな\""
		]
	},
	{
		"TYPE": "BR",
		"UNK0": "30000a000103"
	},
	{
		"TYPE": "PAGEtm",
		"UNK0": "0c000800"
	},
	{
		"TYPE": "EXTEND",
		"UNK0": "0800180002000000000000000000000000000000"
	},
	{
		"TYPE": "PAGE",
		"UNK0": "18000e0000000b004100"
	},
	{
		"STRINGS": [
			"前部座席の二人に気付かれないように、",
			"関本は静かな口調で私に話しかけた。"
		]
	},
	{
		"TYPE": "BR",
		"UNK0": "30000a000103"
	},
	{
		"TYPE": "PAGEtm",
		"UNK0": "0c000800"
	},
	{
		"TYPE": "PAGE",
		"UNK0": "08000e0000000b004200"
	},
	{
		"TYPE": "SPEAKER",
		"UNK0": "10000a00",
		"CHARACTER_ID": 6,
		"NAME": "Houjou Saki"
	},
	{
		"STRINGS": [
			"\"Ｃ村に来た時は、喋ってましたね。",
			"　でもそれが許されているかなんてわかりません\""
		]
	},
	{
		"TYPE": "BR",
		"UNK0": "3c000a000103"
	},
	{
		"TYPE": "PAGEtm",
		"UNK0": "0c000800"
	},
	{
		"TYPE": "PAGE",
		"UNK0": "08000e0000000b004300"
	},
	{
		"TYPE": "SPEAKER",
		"UNK0": "10000a00",
		"CHARACTER_ID": 6,
		"NAME": "Houjou Saki"
	},
	{
		"STRINGS": [
			"\"私達は窓すらない窓際部署の特ラ課です。",
			"　こんな護送をするのは滅多にない事ですから\""
		]
	},
	{
		"TYPE": "BR",
		"UNK0": "38000a000103"
	},
	{
		"TYPE": "PAGEtm",
		"UNK0": "0c000800"
	},
	{
		"TYPE": "EXTEND",
		"UNK0": "0800180002000000000000000000000000000000"
	},
	{
		"TYPE": "CI_LOAD_WAIT",
		"UNK0": "18000a000100"
	},
	{
		"TYPE": "CI_BUSTUP_CENTERING",
		"UNK0": "0c0010000000070701000000"
	},
	{
		"TYPE": "CI_FADE",
		"UNK0": "10001000ffffffff00000100"
	},
	{
		"TYPE": "WAIT",
		"UNK0": "10000a000000"
	},
	{
		"TYPE": "CI_FADE",
		"UNK0": "0c001000ffffff0000000000"
	},
	{
		"TYPE": "WAIT",
		"UNK0": "10000a000000"
	},
	{
		"TYPE": "CI_LOAD",
		"UNK0": "0c000c00800c0000"
	},
	{
		"TYPE": "PAGE",
		"UNK0": "0c000e0000000b004400"
	},
	{
		"TYPE": "SPEAKER",
		"UNK0": "10000a00",
		"CHARACTER_ID": 3,
		"NAME": "Sekimoto Soujirou"
	},
	{
		"STRINGS": [
			"\"そうだな。本来ならば神妙にしているのがいいのだろう。",
			"　だが、これが君と話をする最後のチャンスだと思ってね\""
		]
	},
	{
		"TYPE": "BR",
		"UNK0": "44000a000103"
	},
	{
		"TYPE": "PAGEtm",
		"UNK0": "0c000800"
	},
	{
		"TYPE": "EXTEND",
		"UNK0": "0800180002000000000000000000000000000000"
	},
	{
		"TYPE": "PAGE",
		"UNK0": "18000e0000000b004500"
	},
	{
		"TYPE": "SPEAKER",
		"UNK0": "10000a00",
		"CHARACTER_ID": 6,
		"NAME": "Houjou Saki"
	},
	{
		"STRINGS": [
			"\"同じ事を私も感じていました。",
			"　とはいっても、特に何か話す事はないんですけれども\""
		]
	},
	{
		"TYPE": "BR",
		"UNK0": "40000a000103"
	},
	{
		"TYPE": "PAGEtm",
		"UNK0": "0c000800"
	},
	{
		"TYPE": "PAGE",
		"UNK0": "08000e0000000b004600"
	},
	{
		"TYPE": "SPEAKER",
		"UNK0": "10000a00",
		"CHARACTER_ID": 6,
		"NAME": "Houjou Saki"
	},
	{
		"STRINGS": [
			"\"ただその……ありがとうございました\""
		]
	},
	{
		"TYPE": "BR",
		"UNK0": "34000a000103"
	},
	{
		"TYPE": "PAGEtm",
		"UNK0": "0c000800"
	},
	{
		"TYPE": "EXTEND",
		"UNK0": "0800180002000000000000000000000000000000"
	},
	{
		"TYPE": "CI_LOAD_WAIT",
		"UNK0": "18000a000200"
	},
	{
		"TYPE": "CI_BUSTUP_CENTERING",
		"UNK0": "0c0010000000060702000000"
	},
	{
		"TYPE": "CI_FADE",
		"UNK0": "10001000ffffffff00000200"
	},
	{
		"TYPE": "WAIT",
		"UNK0": "10000a000000"
	},
	{
		"TYPE": "CI_FADE",
		"UNK0": "0c001000ffffff0000000100"
	},
	{
		"TYPE": "WAIT",
		"UNK0": "10000a000000"
	},
	{
		"TYPE": "CI_LOAD",
		"UNK0": "0c000c00a80c0100"
	},
	{
		"TYPE": "PAGE",
		"UNK0": "0c000e0000000b004700"
	},
	{
		"STRINGS": [
			"私は小さく一礼をした。",
			"その様子を見て、彼はふっと笑った。"
		]
	},
	{
		"TYPE": "BR",
		"UNK0": "30000a000103"
	},
	{
		"TYPE": "PAGEtm",
		"UNK0": "0c000800"
	},
	{
		"TYPE": "PAGE",
		"UNK0": "08000e0000000b004800"
	},
	{
		"TYPE": "SPEAKER",
		"UNK0": "10000a00",
		"CHARACTER_ID": 3,
		"NAME": "Sekimoto Soujirou"
	},
	{
		"STRINGS": [
			"\"また、殺人犯に感謝の言葉か。",
			"　前の連中に見られたら問題だぞ\""
		]
	},
	{
		"TYPE": "BR",
		"UNK0": "2c000a000103"
	},
	{
		"TYPE": "PAGEtm",
		"UNK0": "0c000800"
	},
	{
		"TYPE": "EXTEND",
		"UNK0": "0800180002000000000000000000000000000000"
	},
	{
		"TYPE": "PAGE",
		"UNK0": "18000e0000000b004900"
	},
	{
		"TYPE": "SPEAKER",
		"UNK0": "10000a00",
		"CHARACTER_ID": 6,
		"NAME": "Houjou Saki"
	},
	{
		"STRINGS": [
			"\"……もうどうでもいいです\""
		]
	},
	{
		"TYPE": "BR",
		"UNK0": "28000a000103"
	},
	{
		"TYPE": "PAGEtm",
		"UNK0": "0c000800"
	},
	{
		"TYPE": "EXTEND",
		"UNK0": "0800180002000000000000000000000000000000"
	},
	{
		"TYPE": "EXTEND",
		"UNK0": "1800180002000000000000000000000000000000"
	},
	{
		"TYPE": "TXTWND_OUT",
		"UNK0": "18000a001400"
	},
	{
		"TYPE": "WAIT",
		"UNK0": "0c000a001e00"
	},
	{
		"TYPE": "CI_FADE",
		"UNK0": "0c001000ffffff0014000200"
	},
	{
		"TYPE": "WAIT",
		"UNK0": "10000a001400"
	},
	{
		"TYPE": "CI_FADE",
		"UNK0": "0c001000ffffff0000000200"
	},
	{
		"TYPE": "CI_LOAD",
		"UNK0": "10000c00b20c0200"
	},
	{
		"TYPE": "WAIT",
		"UNK0": "0c000a006400"
	},
	{
		"TYPE": "TXTWND_IN",
		"UNK0": "0c000a001400"
	},
	{
		"TYPE": "WAIT",
		"UNK0": "0c000a001e00"
	},
	{
		"TYPE": "PAGE",
		"UNK0": "0c000e0000000b004a00"
	},
	{
		"STRINGS": [
			"そして、沈黙。",
			"わずかな間、私達は何も話さない空虚な時間が続く。"
		]
	},
	{
		"TYPE": "BR",
		"UNK0": "3c000a000103"
	},
	{
		"TYPE": "PAGEtm",
		"UNK0": "0c000800"
	},
	{
		"TYPE": "WAIT",
		"UNK0": "08000a005a00"
	},
	{
		"TYPE": "CI_LOAD_WAIT",
		"UNK0": "0c000a000300"
	},
	{
		"TYPE": "CI_BUSTUP_CENTERING",
		"UNK0": "0c0010000000050703000000"
	},
	{
		"TYPE": "CI_FADE",
		"UNK0": "10001000ffffffff14000300"
	},
	{
		"TYPE": "WAIT",
		"UNK0": "10000a001400"
	},
	{
		"TYPE": "PAGE",
		"UNK0": "0c000e0000000b004b00"
	},
	{
		"TYPE": "SPEAKER",
		"UNK0": "10000a00",
		"CHARACTER_ID": 3,
		"NAME": "Sekimoto Soujirou"
	},
	{
		"STRINGS": [
			"\"君達への協力の理由——",
			"　ブラインドマンの正体をこの目で見極めたいと私は言った。",
			"　だが、それは正確じゃない\""
		]
	},
	{
		"TYPE": "BR",
		"UNK0": "28000a000103"
	},
	{
		"TYPE": "PAGEtm",
		"UNK0": "0c000800"
	},
	{
		"TYPE": "EXTEND",
		"UNK0": "0800180002000000000000000000000000000000"
	},
	{
		"TYPE": "PAGE",
		"UNK0": "18000e0000000b004c00"
	},
	{
		"STRINGS": [
			"唐突に語りはじめた言葉に、",
			"私は思わず彼の方を向いた。"
		]
	},
	{
		"TYPE": "BR",
		"UNK0": "28000a000103"
	},
	{
		"TYPE": "PAGEtm",
		"UNK0": "0c000800"
	},
	{
		"TYPE": "PAGE",
		"UNK0": "08000e0000000b004d00"
	},
	{
		"TYPE": "SPEAKER",
		"UNK0": "10000a00",
		"CHARACTER_ID": 6,
		"NAME": "Houjou Saki"
	},
	{
		"STRINGS": [
			"\"それは……どういう事ですか？\""
		]
	},
	{
		"TYPE": "BR",
		"UNK0": "2c000a000103"
	},
	{
		"TYPE": "PAGEtm",
		"UNK0": "0c000800"
	},
	{
		"TYPE": "EXTEND",
		"UNK0": "0800180002000000000000000000000000000000"
	},
	{
		"TYPE": "PAGE",
		"UNK0": "18000e0000000b004e00"
	},
	{
		"TYPE": "SPEAKER",
		"UNK0": "10000a00",
		"CHARACTER_ID": 3,
		"NAME": "Sekimoto Soujirou"
	},
	{
		"STRINGS": [
			"\"もちろん、ブラインドマンを利用した輩の正体を知りたい",
			"　のは事実だ。",
			"　本人の心理を探れば、やりかけた研究に進展が望めるから\""
		]
	},
	{
		"TYPE": "BR",
		"UNK0": "44000a000103"
	},
	{
		"TYPE": "PAGEtm",
		"UNK0": "0c000800"
	},
	{
		"TYPE": "CI_LOAD_WAIT",
		"UNK0": "08000a000000"
	},
	{
		"TYPE": "CI_BUSTUP_CENTERING",
		"UNK0": "0c0010000000080700000000"
	},
	{
		"TYPE": "CI_FADE",
		"UNK0": "10001000ffffffff00000000"
	},
	{
		"TYPE": "WAIT",
		"UNK0": "10000a000000"
	},
	{
		"TYPE": "CI_FADE",
		"UNK0": "0c001000ffffff0000000300"
	},
	{
		"TYPE": "WAIT",
		"UNK0": "10000a000000"
	},
	{
		"TYPE": "CI_LOAD",
		"UNK0": "0c000c008a0c0300"
	},
	{
		"TYPE": "PAGE",
		"UNK0": "0c000e0000000b004f00"
	},
	{
		"TYPE": "SPEAKER",
		"UNK0": "10000a00",
		"CHARACTER_ID": 3,
		"NAME": "Sekimoto Soujirou"
	},
	{
		"STRINGS": [
			"\"しかし、私の真意はまだある。",
			"　だからといって、私はその怪物を野に放ちたかったわけ",
			"　ではない\""
		]
	},
	{
		"TYPE": "BR",
		"UNK0": "18000a000103"
	},
	{
		"TYPE": "PAGEtm",
		"UNK0": "0c000800"
	},
	{
		"TYPE": "PAGE",
		"UNK0": "08000e0000000b005000"
	},
	{
		"TYPE": "SPEAKER",
		"UNK0": "10000a00",
		"CHARACTER_ID": 3,
		"NAME": "Sekimoto Soujirou"
	},
	{
		"STRINGS": [
			"\"私はただ、ブラインドマンとその恐怖を人々の心に",
			"　芽生えさせたかっただけだ。",
			"　決して、こんな事件は望んじゃいない\""
		]
	},
	{
		"TYPE": "BR",
		"UNK0": "34000a000103"
	},
	{
		"TYPE": "PAGEtm",
		"UNK0": "0c000800"
	},
	{
		"TYPE": "CI_LOAD_WAIT",
		"UNK0": "08000a000100"
	},
	{
		"TYPE": "CI_BUSTUP_CENTERING",
		"UNK0": "0c0010000000070701000000"
	},
	{
		"TYPE": "CI_FADE",
		"UNK0": "10001000ffffffff00000100"
	},
	{
		"TYPE": "WAIT",
		"UNK0": "10000a000000"
	},
	{
		"TYPE": "CI_FADE",
		"UNK0": "0c001000ffffff0000000000"
	},
	{
		"TYPE": "WAIT",
		"UNK0": "10000a000000"
	},
	{
		"TYPE": "CI_LOAD",
		"UNK0": "0c000c00b20c0000"
	},
	{
		"TYPE": "PAGE",
		"UNK0": "0c000e0000000b005100"
	},
	{
		"TYPE": "SPEAKER",
		"UNK0": "10000a00",
		"CHARACTER_ID": 3,
		"NAME": "Sekimoto Soujirou"
	},
	{
		"STRINGS": [
			"\"しかし実際に現実世界に生まれてしまった。",
			"　ブラインドマンの名を背負って凶行を繰り返す怪物を。",
			"　それに関して私は心を痛めている\""
		]
	},
	{
		"TYPE": "BR",
		"UNK0": "30000a000103"
	},
	{
		"TYPE": "PAGEtm",
		"UNK0": "0c000800"
	},
	{
		"TYPE": "EXTEND",
		"UNK0": "0800180002000000000000000000000000000000"
	},
	{
		"TYPE": "PAGE",
		"UNK0": "18000e0000000b005200"
	},
	{
		"TYPE": "SPEAKER",
		"UNK0": "10000a00",
		"CHARACTER_ID": 6,
		"NAME": "Houjou Saki"
	},
	{
		"STRINGS": [
			"\"あなたはもっとドライな方だと思っていました\""
		]
	},
	{
		"TYPE": "BR",
		"UNK0": "3c000a000103"
	},
	{
		"TYPE": "PAGEtm",
		"UNK0": "0c000800"
	},
	{
		"TYPE": "EXTEND",
		"UNK0": "0800180002000000000000000000000000000000"
	},
	{
		"TYPE": "CI_LOAD_WAIT",
		"UNK0": "18000a000200"
	},
	{
		"TYPE": "CI_BUSTUP_CENTERING",
		"UNK0": "0c0010000000060702000000"
	},
	{
		"TYPE": "CI_FADE",
		"UNK0": "10001000ffffffff00000200"
	},
	{
		"TYPE": "WAIT",
		"UNK0": "10000a000000"
	},
	{
		"TYPE": "CI_FADE",
		"UNK0": "0c001000ffffff0000000100"
	},
	{
		"TYPE": "WAIT",
		"UNK0": "10000a000000"
	},
	{
		"TYPE": "CI_LOAD",
		"UNK0": "0c000c00a80c0100"
	},
	{
		"TYPE": "PAGE",
		"UNK0": "0c000e0000000b005300"
	},
	{
		"TYPE": "SPEAKER",
		"UNK0": "10000a00",
		"CHARACTER_ID": 3,
		"NAME": "Sekimoto Soujirou"
	},
	{
		"STRINGS": [
			"\"人は私をマッドサイエンティストだとか冷血だとか",
			"　揶揄をする。",
			"　だが私だって人間だ。人の心はある\""
		]
	},
	{
		"TYPE": "BR",
		"UNK0": "30000a000103"
	},
	{
		"TYPE": "PAGEtm",
		"UNK0": "0c000800"
	},
	{
		"TYPE": "PAGE",
		"UNK0": "08000e0000000b005400"
	},
	{
		"TYPE": "SPEAKER",
		"UNK0": "10000a00",
		"CHARACTER_ID": 3,
		"NAME": "Sekimoto Soujirou"
	},
	{
		"STRINGS": [
			"\"責任を感じているんだ。",
			"　不覚にも自分が生み出した怪物の責任を取りたかったんだ。",
			"　だから、公判で口を開いた\""
		]
	},
	{
		"TYPE": "BR",
		"UNK0": "28000a000103"
	},
	{
		"TYPE": "PAGEtm",
		"UNK0": "0c000800"
	},
	{
		"TYPE": "PAGE",
		"UNK0": "08000e0000000b005500"
	},
	{
		"TYPE": "SPEAKER",
		"UNK0": "10000a00",
		"CHARACTER_ID": 3,
		"NAME": "Sekimoto Soujirou"
	},
	{
		"STRINGS": [
			"\"あの場が一番、私の発言が注目されるからだ。",
			"　もしマスコミが取り上げたら、黙殺する",
			"　わけにはいかないからな\""
		]
	},
	{
		"TYPE": "BR",
		"UNK0": "28000a000103"
	},
	{
		"TYPE": "PAGEtm",
		"UNK0": "0c000800"
	},
	{
		"TYPE": "EXTEND",
		"UNK0": "0800180002000000000000000000000000000000"
	},
	{
		"TYPE": "PAGE",
		"UNK0": "18000e0000000b005600"
	},
	{
		"TYPE": "SPEAKER",
		"UNK0": "10000a00",
		"CHARACTER_ID": 6,
		"NAME": "Houjou Saki"
	},
	{
		"STRINGS": [
			"\"前にも同じ事を言いましたね。",
			"　責任……でも、具体的には？\""
		]
	},
	{
		"TYPE": "BR",
		"UNK0": "2c000a000103"
	},
	{
		"TYPE": "PAGEtm",
		"UNK0": "0c000800"
	},
	{
		"TYPE": "EXTEND",
		"UNK0": "0800180002000000000000000000000000000000"
	},
	{
		"TYPE": "CI_LOAD_WAIT",
		"UNK0": "18000a000300"
	},
	{
		"TYPE": "CI_BUSTUP_CENTERING",
		"UNK0": "0c0010000000050703000000"
	},
	{
		"TYPE": "CI_FADE",
		"UNK0": "10001000ffffffff00000300"
	},
	{
		"TYPE": "WAIT",
		"UNK0": "10000a000000"
	},
	{
		"TYPE": "CI_FADE",
		"UNK0": "0c001000ffffff0000000200"
	},
	{
		"TYPE": "WAIT",
		"UNK0": "10000a000000"
	},
	{
		"TYPE": "CI_LOAD",
		"UNK0": "0c000c008a0c0200"
	},
	{
		"TYPE": "PAGE",
		"UNK0": "0c000e0000000b005700"
	},
	{
		"TYPE": "SPEAKER",
		"UNK0": "10000a00",
		"CHARACTER_ID": 3,
		"NAME": "Sekimoto Soujirou"
	},
	{
		"STRINGS": [
			"\"怪物の生みの親として、人の道を教えてやるのもいい。",
			"　もしくは、怪物として力を振るう方法を教えてやるのも",
			"　悪くない\""
		]
	},
	{
		"TYPE": "BR",
		"UNK0": "18000a000103"
	},
	{
		"TYPE": "PAGEtm",
		"UNK0": "0c000800"
	},
	{
		"TYPE": "EXTEND",
		"UNK0": "0800180002000000000000000000000000000000"
	},
	{
		"TYPE": "PAGE",
		"UNK0": "18000e0000000b005800"
	},
	{
		"STRINGS": [
			"私は思わず関本を覗き込んだ。",
			"彼は私を一瞥もせずに前を向いている。"
		]
	},
	{
		"TYPE": "BR",
		"UNK0": "30000a000103"
	},
	{
		"TYPE": "PAGEtm",
		"UNK0": "0c000800"
	},
	{
		"TYPE": "PAGE",
		"UNK0": "08000e0000000b005900"
	},
	{
		"TYPE": "SPEAKER",
		"UNK0": "10000a00",
		"CHARACTER_ID": 6,
		"NAME": "Houjou Saki"
	},
	{
		"STRINGS": [
			"\"怪物として力を振るう方法を教える……って、",
			"　どういう……意味ですか\""
		]
	},
	{
		"TYPE": "BR",
		"UNK0": "28000a000103"
	},
	{
		"TYPE": "PAGEtm",
		"UNK0": "0c000800"
	},
	{
		"TYPE": "EXTEND",
		"UNK0": "0800180002000000000000000000000000000000"
	},
	{
		"TYPE": "CI_LOAD_WAIT",
		"UNK0": "18000a000000"
	},
	{
		"TYPE": "CI_BUSTUP_CENTERING",
		"UNK0": "0c0010000000080700000000"
	},
	{
		"TYPE": "CI_FADE",
		"UNK0": "10001000ffffffff00000000"
	},
	{
		"TYPE": "WAIT",
		"UNK0": "10000a000000"
	},
	{
		"TYPE": "CI_FADE",
		"UNK0": "0c001000ffffff0000000300"
	},
	{
		"TYPE": "WAIT",
		"UNK0": "10000a000000"
	},
	{
		"TYPE": "CI_LOAD",
		"UNK0": "0c000c00b20c0300"
	},
	{
		"TYPE": "PAGE",
		"UNK0": "0c000e0000000b005a00"
	},
	{
		"TYPE": "SPEAKER",
		"UNK0": "10000a00",
		"CHARACTER_ID": 3,
		"NAME": "Sekimoto Soujirou"
	},
	{
		"STRINGS": [
			"\"この世に生まれた者は、全て目的がある。",
			"　だからブラインドマンにもそれを与えようというのだ。",
			"　この生みの親の私が\""
		]
	},
	{
		"TYPE": "BR",
		"UNK0": "24000a000103"
	},
	{
		"TYPE": "PAGEtm",
		"UNK0": "0c000800"
	},
	{
		"TYPE": "EXTEND",
		"UNK0": "0800180002000000000000000000000000000000"
	},
	{
		"TYPE": "PAGE",
		"UNK0": "18000e0000000b005b00"
	},
	{
		"TYPE": "SPEAKER",
		"UNK0": "10000a00",
		"CHARACTER_ID": 6,
		"NAME": "Houjou Saki"
	},
	{
		"STRINGS": [
			"\"それは殺戮を繰り返せという事ですか\""
		]
	},
	{
		"TYPE": "BR",
		"UNK0": "34000a000103"
	},
	{
		"TYPE": "PAGEtm",
		"UNK0": "0c000800"
	},
	{
		"TYPE": "EXTEND",
		"UNK0": "0800180002000000000000000000000000000000"
	},
	{
		"TYPE": "CI_LOAD_WAIT",
		"UNK0": "18000a000100"
	},
	{
		"TYPE": "CI_BUSTUP_CENTERING",
		"UNK0": "0c0010000000070701000000"
	},
	{
		"TYPE": "CI_FADE",
		"UNK0": "10001000ffffffff00000100"
	},
	{
		"TYPE": "WAIT",
		"UNK0": "10000a000000"
	},
	{
		"TYPE": "CI_FADE",
		"UNK0": "0c001000ffffff0000000000"
	},
	{
		"TYPE": "WAIT",
		"UNK0": "10000a000000"
	},
	{
		"TYPE": "CI_LOAD",
		"UNK0": "0c000c008a0c0000"
	},
	{
		"TYPE": "PAGE",
		"UNK0": "0c000e0000000b005c00"
	},
	{
		"STRINGS": [
			"関本はため息をついた。"
		]
	},
	{
		"TYPE": "BR",
		"UNK0": "28000a000103"
	},
	{
		"TYPE": "PAGEtm",
		"UNK0": "0c000800"
	},
	{
		"TYPE": "CI_LOAD_WAIT",
		"UNK0": "08000a000200"
	},
	{
		"TYPE": "CI_BUSTUP_CENTERING",
		"UNK0": "0c0010000000060702000000"
	},
	{
		"TYPE": "CI_FADE",
		"UNK0": "10001000ffffffff00000200"
	},
	{
		"TYPE": "WAIT",
		"UNK0": "10000a000000"
	},
	{
		"TYPE": "CI_FADE",
		"UNK0": "0c001000ffffff0000000100"
	},
	{
		"TYPE": "WAIT",
		"UNK0": "10000a000000"
	},
	{
		"TYPE": "CI_LOAD",
		"UNK0": "0c000c00800c0100"
	},
	{
		"TYPE": "PAGE",
		"UNK0": "0c000e0000000b005d00"
	},
	{
		"TYPE": "SPEAKER",
		"UNK0": "10000a00",
		"CHARACTER_ID": 3,
		"NAME": "Sekimoto Soujirou"
	},
	{
		"STRINGS": [
			"\"……君は私と話していて何を学んだんだ\""
		]
	},
	{
		"TYPE": "BR",
		"UNK0": "34000a000103"
	},
	{
		"TYPE": "PAGEtm",
		"UNK0": "0c000800"
	},
	{
		"TYPE": "CI_LOAD_WAIT",
		"UNK0": "08000a000300"
	},
	{
		"TYPE": "CI_BUSTUP_CENTERING",
		"UNK0": "0c0010000000050703000000"
	},
	{
		"TYPE": "CI_FADE",
		"UNK0": "10001000ffffffff00000300"
	},
	{
		"TYPE": "WAIT",
		"UNK0": "10000a000000"
	},
	{
		"TYPE": "CI_FADE",
		"UNK0": "0c001000ffffff0000000200"
	},
	{
		"TYPE": "WAIT",
		"UNK0": "10000a000000"
	},
	{
		"TYPE": "CI_LOAD",
		"UNK0": "0c000c00ce130200"
	},
	{
		"TYPE": "PAGE",
		"UNK0": "0c000e0000000b005e00"
	},
	{
		"TYPE": "SPEAKER",
		"UNK0": "10000a00",
		"CHARACTER_ID": 3,
		"NAME": "Sekimoto Soujirou"
	},
	{
		"STRINGS": [
			"\"私は民俗学、都市伝説の研究者にすぎない。",
			"　殺しのスペシャリストではない\""
		]
	},
	{
		"TYPE": "BR",
		"UNK0": "2c000a000103"
	},
	{
		"TYPE": "PAGEtm",
		"UNK0": "0c000800"
	},
	{
		"TYPE": "PAGE",
		"UNK0": "08000e0000000b005f00"
	},
	{
		"TYPE": "SPEAKER",
		"UNK0": "10000a00",
		"CHARACTER_ID": 3,
		"NAME": "Sekimoto Soujirou"
	},
	{
		"STRINGS": [
			"\"殺しに関してはブラインドマンの方が上手だ。",
			"　私が出来るのは奴に動機を与えるぐらいだよ\""
		]
	},
	{
		"TYPE": "BR",
		"UNK0": "38000a000103"
	},
	{
		"TYPE": "PAGEtm",
		"UNK0": "0c000800"
	},
	{
		"TYPE": "EXTEND",
		"UNK0": "0800180002000000000000000000000000000000"
	},
	{
		"TYPE": "PAGE",
		"UNK0": "18000e0000000b006000"
	},
	{
		"TYPE": "SPEAKER",
		"UNK0": "10000a00",
		"CHARACTER_ID": 6,
		"NAME": "Houjou Saki"
	},
	{
		"STRINGS": [
			"\"同じじゃないですか。",
			"　都市伝説を介して人々の心の中でブラインドマンを",
			"　生かすために、今回の事件を利用しようとしている\""
		]
	},
	{
		"TYPE": "BR",
		"UNK0": "40000a000103"
	},
	{
		"TYPE": "PAGEtm",
		"UNK0": "0c000800"
	},
	{
		"TYPE": "PAGE",
		"UNK0": "08000e0000000b006100"
	},
	{
		"TYPE": "SPEAKER",
		"UNK0": "10000a00",
		"CHARACTER_ID": 6,
		"NAME": "Houjou Saki"
	},
	{
		"STRINGS": [
			"\"架空の存在のはずのブラインドマンに、",
			"　命を吹き込む事で、あなたは自己顕示欲を",
			"　満たしたいんですか？\""
		]
	},
	{
		"TYPE": "BR",
		"UNK0": "24000a000103"
	},
	{
		"TYPE": "PAGEtm",
		"UNK0": "0c000800"
	},
	{
		"TYPE": "EXTEND",
		"UNK0": "0800180002000000000000000000000000000000"
	},
	{
		"TYPE": "CI_LOAD_WAIT",
		"UNK0": "18000a000000"
	},
	{
		"TYPE": "CI_BUSTUP_CENTERING",
		"UNK0": "0c0010000000080700000000"
	},
	{
		"TYPE": "CI_FADE",
		"UNK0": "10001000ffffffff00000000"
	},
	{
		"TYPE": "WAIT",
		"UNK0": "10000a000000"
	},
	{
		"TYPE": "CI_FADE",
		"UNK0": "0c001000ffffff0000000300"
	},
	{
		"TYPE": "WAIT",
		"UNK0": "10000a000000"
	},
	{
		"TYPE": "CI_LOAD",
		"UNK0": "0c000c00ba130300"
	},
	{
		"TYPE": "PAGE",
		"UNK0": "0c000e0000000b006200"
	},
	{
		"TYPE": "SPEAKER",
		"UNK0": "10000a00",
		"CHARACTER_ID": 3,
		"NAME": "Sekimoto Soujirou"
	},
	{
		"STRINGS": [
			"\"…………\""
		]
	},
	{
		"TYPE": "BR",
		"UNK0": "18000a000103"
	},
	{
		"TYPE": "PAGEtm",
		"UNK0": "0c000800"
	},
	{
		"TYPE": "EXTEND",
		"UNK0": "0800180002000000000000000000000000000000"
	},
	{
		"TYPE": "PAGE",
		"UNK0": "18000e0000000b006300"
	},
	{
		"TYPE": "SPEAKER",
		"UNK0": "10000a00",
		"CHARACTER_ID": 6,
		"NAME": "Houjou Saki"
	},
	{
		"STRINGS": [
			"\"…………\""
		]
	},
	{
		"TYPE": "BR",
		"UNK0": "18000a000103"
	},
	{
		"TYPE": "PAGEtm",
		"UNK0": "0c000800"
	},
	{
		"TYPE": "PAGE",
		"UNK0": "08000e0000000b006400"
	},
	{
		"STRINGS": [
			"関本は黙ったまま、私を見つめていた。",
			"私は彼が返事をするまで、彼に鋭い視線を",
			"投げかけていた。"
		]
	},
	{
		"TYPE": "BR",
		"UNK0": "1c000a000103"
	},
	{
		"TYPE": "PAGEtm",
		"UNK0": "0c000800"
	},
	{
		"TYPE": "PAGE",
		"UNK0": "08000e0000000b006500"
	},
	{
		"STRINGS": [
			"私は、関本爽二朗を誤解していたのかもしれない。"
		]
	},
	{
		"TYPE": "BR",
		"UNK0": "40000a000103"
	},
	{
		"TYPE": "PAGEtm",
		"UNK0": "0c000800"
	},
	{
		"TYPE": "PAGE",
		"UNK0": "08000e0000000b006600"
	},
	{
		"STRINGS": [
			"事件の進展に伴い、彼は奇想天外な視点から、",
			"多くの示唆を与えてくれた。",
			"実際、それが具体的な成果となって役に立った。"
		]
	},
	{
		"TYPE": "BR",
		"UNK0": "38000a000103"
	},
	{
		"TYPE": "PAGEtm",
		"UNK0": "0c000800"
	},
	{
		"TYPE": "PAGE",
		"UNK0": "08000e0000000b006700"
	},
	{
		"STRINGS": [
			"風守さんの殉職の時だってそうだ。",
			"くじけそうな私に、厳しい言葉で叱咤激励をしてくれた。"
		]
	},
	{
		"TYPE": "BR",
		"UNK0": "40000a000103"
	},
	{
		"TYPE": "PAGEtm",
		"UNK0": "0c000800"
	},
	{
		"TYPE": "PAGE",
		"UNK0": "08000e0000000b006800"
	},
	{
		"STRINGS": [
			"これらを通じて、私は彼に対する認識を徐々に",
			"改めていった。"
		]
	},
	{
		"TYPE": "BR",
		"UNK0": "1c000a000103"
	},
	{
		"TYPE": "PAGEtm",
		"UNK0": "0c000800"
	},
	{
		"TYPE": "PAGE",
		"UNK0": "08000e0000000b006900"
	},
	{
		"STRINGS": [
			"だが、その正体はやはりただの変人なのか。",
			"信じるに値しない人間なのだろうか？"
		]
	},
	{
		"TYPE": "BR",
		"UNK0": "30000a000103"
	},
	{
		"TYPE": "PAGEtm",
		"UNK0": "0c000800"
	},
	{
		"TYPE": "PAGE",
		"UNK0": "08000e0000000b006a00"
	},
	{
		"TYPE": "SPEAKER",
		"UNK0": "10000a00",
		"CHARACTER_ID": 6,
		"NAME": "Houjou Saki"
	},
	{
		"STRINGS": [
			"\"答えてください。",
			"　あなたは、本音としてブラインドマンによる更なる殺戮を",
			"　望んでいるんですか？\""
		]
	},
	{
		"TYPE": "BR",
		"UNK0": "24000a000103"
	},
	{
		"TYPE": "PAGEtm",
		"UNK0": "0c000800"
	},
	{
		"TYPE": "EXTEND",
		"UNK0": "0800180002000000000000000000000000000000"
	},
	{
		"TYPE": "CI_LOAD_WAIT",
		"UNK0": "18000a000100"
	},
	{
		"TYPE": "CI_BUSTUP_CENTERING",
		"UNK0": "0c0010000000070701000000"
	},
	{
		"TYPE": "CI_FADE",
		"UNK0": "10001000ffffffff00000100"
	},
	{
		"TYPE": "WAIT",
		"UNK0": "10000a000000"
	},
	{
		"TYPE": "CI_FADE",
		"UNK0": "0c001000ffffff0000000000"
	},
	{
		"TYPE": "WAIT",
		"UNK0": "10000a000000"
	},
	{
		"TYPE": "CI_LOAD",
		"UNK0": "0c000c00ce130000"
	},
	{
		"TYPE": "PAGE",
		"UNK0": "0c000e0000000b006b00"
	},
	{
		"TYPE": "SPEAKER",
		"UNK0": "10000a00",
		"CHARACTER_ID": 3,
		"NAME": "Sekimoto Soujirou"
	},
	{
		"STRINGS": [
			"\"……さあ、それはどうだろうな。",
			"　自分で考えるんだな\""
		]
	},
	{
		"TYPE": "BR",
		"UNK0": "24000a000103"
	},
	{
		"TYPE": "PAGEtm",
		"UNK0": "0c000800"
	},
	{
		"TYPE": "EXTEND",
		"UNK0": "0800180002000000000000000000000000000000"
	},
	{
		"TYPE": "CI_FADE",
		"UNK0": "18001000ffffff0014000100"
	},
	{
		"TYPE": "WAIT",
		"UNK0": "10000a001400"
	},
	{
		"TYPE": "CI_FADE",
		"UNK0": "0c001000ffffff0000000100"
	},
	{
		"TYPE": "CI_LOAD",
		"UNK0": "10000c00ba130100"
	},
	{
		"TYPE": "BGM_VOL",
		"UNK0": "0c000c001e000000"
	},
	{
		"TYPE": "WAIT",
		"UNK0": "0c000a001e00"
	},
	{
		"TYPE": "BGM_VOL",
		"UNK0": "0c000c0000000000"
	},
	{
		"TYPE": "BGM_STOP",
		"UNK0": "0c000800"
	},
	{
		"TYPE": "PAGE",
		"UNK0": "08000e0000000b006c00"
	},
	{
		"TYPE": "SPEAKER",
		"UNK0": "10000a00",
		"CHARACTER_ID": 7,
		"NAME": "Kuroda Kunio"
	},
	{
		"STRINGS": [
			"\"おわっと、あぶなっ！！\""
		]
	},
	{
		"TYPE": "BR",
		"UNK0": "28000a000103"
	},
	{
		"TYPE": "PAGEtm",
		"UNK0": "0c000800"
	},
	{
		"TYPE": "EXTEND",
		"UNK0": "0800180002000000000000000000000000000000"
	},
	{
		"TYPE": "SCR_VIB",
		"UNK0": "18000e000f0001010f00"
	},
	{
		"TYPE": "LOOPS_VOL",
		"UNK0": "10000e0000001e000000"
	},
	{
		"TYPE": "SE_PLAY",
		"UNK0": "10000e002f0280800000"
	},
	{
		"TYPE": "PAD_VIB",
		"UNK0": "10000e001e000001c800"
	},
	{
		"TYPE": "WAIT",
		"UNK0": "10000a001e00"
	},
	{
		"TYPE": "LOOPS_VOL",
		"UNK0": "0c000e00000000000000"
	},
	{
		"TYPE": "LOOPS_STOP",
		"UNK0": "10000a000000"
	},
	{
		"TYPE": "LOOPS_READY",
		"UNK0": "0c000c0026020000"
	},
	{
		"TYPE": "WAIT",
		"UNK0": "0c000a000a00"
	},
	{
		"TYPE": "LOOPS_WAIT",
		"UNK0": "0c000a000000"
	},
	{
		"TYPE": "LOOPS_PLAY",
		"UNK0": "0c0010002602000000000000"
	},
	{
		"TYPE": "LOOPS_VOL",
		"UNK0": "10000e003c0000000000"
	},
	{
		"TYPE": "PAGE",
		"UNK0": "10000e0000000b006d00"
	},
	{
		"STRINGS": [
			"ボックスカーは急ブレーキをして、",
			"私達の身体が一瞬だけ宙に浮いた。"
		]
	},
	{
		"TYPE": "BR",
		"UNK0": "2c000a000103"
	},
	{
		"TYPE": "PAGEtm",
		"UNK0": "0c000800"
	},
	{
		"TYPE": "PAGE",
		"UNK0": "08000e0000000b006e00"
	},
	{
		"TYPE": "SPEAKER",
		"UNK0": "10000a00",
		"CHARACTER_ID": 6,
		"NAME": "Houjou Saki"
	},
	{
		"STRINGS": [
			"\"どうしたんですか？\""
		]
	},
	{
		"TYPE": "BR",
		"UNK0": "24000a000103"
	},
	{
		"TYPE": "PAGEtm",
		"UNK0": "0c000800"
	},
	{
		"TYPE": "EXTEND",
		"UNK0": "0800180002000000000000000000000000000000"
	},
	{
		"TYPE": "CI_LOAD_WAIT",
		"UNK0": "18000a000200"
	},
	{
		"TYPE": "CI_BUSTUP_CENTERING",
		"UNK0": "0c0010000000060702000000"
	},
	{
		"TYPE": "CI_FADE",
		"UNK0": "10001000ffffffff14000200"
	},
	{
		"TYPE": "WAIT",
		"UNK0": "10000a001400"
	},
	{
		"TYPE": "PAGE",
		"UNK0": "0c000e0000000b006f00"
	},
	{
		"TYPE": "SPEAKER",
		"UNK0": "10000a00",
		"CHARACTER_ID": 7,
		"NAME": "Kuroda Kunio"
	},
	{
		"STRINGS": [
			"\"なんだ……あれ……？\""
		]
	},
	{
		"TYPE": "BR",
		"UNK0": "24000a000103"
	},
	{
		"TYPE": "PAGEtm",
		"UNK0": "0c000800"
	},
	{
		"TYPE": "EXTEND",
		"UNK0": "0800180002000000000000000000000000000000"
	},
	{
		"TYPE": "EXTEND",
		"UNK0": "1800180002000000000000000000000000000000"
	},
	{
		"TYPE": "TXTWND_OUT",
		"UNK0": "18000a001400"
	},
	{
		"TYPE": "WAIT",
		"UNK0": "0c000a001e00"
	},
	{
		"TYPE": "CI_FADE",
		"UNK0": "0c001000ffffff0014000200"
	},
	{
		"TYPE": "WAIT",
		"UNK0": "10000a001400"
	},
	{
		"TYPE": "CI_FADE",
		"UNK0": "0c001000ffffff0000000200"
	},
	{
		"TYPE": "BG_FADE",
		"UNK0": "10001000404040801e000300"
	},
	{
		"TYPE": "WAIT",
		"UNK0": "10000a001e00"
	},
	{
		"TYPE": "SE_PLAY",
		"UNK0": "0c000e006e0080800000"
	},
	{
		"TYPE": "CI_LOAD",
		"UNK0": "10000c00524e0400"
	},
	{
		"TYPE": "CI_LOAD_WAIT",
		"UNK0": "0c000a000400"
	},
	{
		"TYPE": "CI_MOVE",
		"UNK0": "0c0012002c01ceff400600000400"
	},
	{
		"TYPE": "CI_FADE",
		"UNK0": "140010008080800000000400"
	},
	{
		"TYPE": "CI_FADE",
		"UNK0": "10001000808080803c000400"
	},
	{
		"TYPE": "WAIT",
		"UNK0": "10000a005a00"
	},
	{
		"TYPE": "TXTWND_IN",
		"UNK0": "0c000a001400"
	},
	{
		"TYPE": "WAIT",
		"UNK0": "0c000a001e00"
	},
	{
		"TYPE": "PAGE",
		"UNK0": "0c000e0000000b007000"
	},
	{
		"STRINGS": [
			"黒田課長は前方を指さした。",
			"目の前に何かいる。"
		]
	},
	{
		"TYPE": "BR",
		"UNK0": "20000a000103"
	},
	{
		"TYPE": "PAGEtm",
		"UNK0": "0c000800"
	},
	{
		"TYPE": "PAGE",
		"UNK0": "08000e0000000b007100"
	},
	{
		"TYPE": "SPEAKER",
		"UNK0": "10000a00",
		"CHARACTER_ID": 6,
		"NAME": "Houjou Saki"
	},
	{
		"STRINGS": [
			"\"人……ですか？\""
		]
	},
	{
		"TYPE": "BR",
		"UNK0": "20000a000103"
	},
	{
		"TYPE": "PAGEtm",
		"UNK0": "0c000800"
	},
	{
		"TYPE": "EXTEND",
		"UNK0": "0800180002000000000000000000000000000000"
	},
	{
		"TYPE": "PAGE",
		"UNK0": "18000e0000000b007200"
	},
	{
		"STRINGS": [
			"人だと口にしてみるものの、",
			"自分で確信にまで至らない。"
		]
	},
	{
		"TYPE": "BR",
		"UNK0": "28000a000103"
	},
	{
		"TYPE": "PAGEtm",
		"UNK0": "0c000800"
	},
	{
		"TYPE": "PAGE",
		"UNK0": "08000e0000000b007300"
	},
	{
		"STRINGS": [
			"それはあまりにも奇妙な出で立ちだったからだ。"
		]
	},
	{
		"TYPE": "BR",
		"UNK0": "3c000a000103"
	},
	{
		"TYPE": "PAGEtm",
		"UNK0": "0c000800"
	},
	{
		"TYPE": "PAGE",
		"UNK0": "08000e0000000b007400"
	},
	{
		"STRINGS": [
			"その前方にいる『なにか』は、",
			"ボロボロの布を全身に纏っていた。"
		]
	},
	{
		"TYPE": "BR",
		"UNK0": "2c000a000103"
	},
	{
		"TYPE": "PAGEtm",
		"UNK0": "0c000800"
	},
	{
		"TYPE": "EXTEND",
		"UNK0": "0800180002000000000000000000000000000000"
	},
	{
		"TYPE": "TXTWND_OUT",
		"UNK0": "18000a001400"
	},
	{
		"TYPE": "WAIT",
		"UNK0": "0c000a001e00"
	},
	{
		"TYPE": "CI_FADE",
		"UNK0": "0c001000808080001e000400"
	},
	{
		"TYPE": "WAIT",
		"UNK0": "10000a001e00"
	},
	{
		"TYPE": "BG_FADE",
		"UNK0": "0c001000808080801e000300"
	},
	{
		"TYPE": "WAIT",
		"UNK0": "10000a001e00"
	},
	{
		"TYPE": "CI_LOAD_WAIT",
		"UNK0": "0c000a000000"
	},
	{
		"TYPE": "CI_BUSTUP_CENTERING",
		"UNK0": "0c0010000000080700000000"
	},
	{
		"TYPE": "CI_FADE",
		"UNK0": "10001000ffffffff14000000"
	},
	{
		"TYPE": "WAIT",
		"UNK0": "10000a001400"
	},
	{
		"TYPE": "TXTWND_IN",
		"UNK0": "0c000a001400"
	},
	{
		"TYPE": "WAIT",
		"UNK0": "0c000a001e00"
	},
	{
		"TYPE": "PAGE",
		"UNK0": "0c000e0000000b007500"
	},
	{
		"TYPE": "SPEAKER",
		"UNK0": "10000a00",
		"CHARACTER_ID": 7,
		"NAME": "Kuroda Kunio"
	},
	{
		"STRINGS": [
			"\"まさか私達は狐か狸に化かされているのかな。",
			"　こんな場所に人がいるはずもないだろう\""
		]
	},
	{
		"TYPE": "BR",
		"UNK0": "34000a000103"
	},
	{
		"TYPE": "PAGEtm",
		"UNK0": "0c000800"
	},
	{
		"TYPE": "PAGE",
		"UNK0": "08000e0000000b007600"
	},
	{
		"STRINGS": [
			"たしかにここは人気があるはずもない山道だ。",
			"日が暮れたこんな時間に人がいるなんて考えにくい。"
		]
	},
	{
		"TYPE": "BR",
		"UNK0": "3c000a000103"
	},
	{
		"TYPE": "PAGEtm",
		"UNK0": "0c000800"
	},
	{
		"TYPE": "CI_LOAD_WAIT",
		"UNK0": "08000a000100"
	},
	{
		"TYPE": "CI_BUSTUP_CENTERING",
		"UNK0": "0c0010000000070701000000"
	},
	{
		"TYPE": "CI_FADE",
		"UNK0": "10001000ffffffff00000100"
	},
	{
		"TYPE": "WAIT",
		"UNK0": "10000a000000"
	},
	{
		"TYPE": "CI_FADE",
		"UNK0": "0c001000ffffff0000000000"
	},
	{
		"TYPE": "WAIT",
		"UNK0": "10000a000000"
	},
	{
		"TYPE": "CI_LOAD",
		"UNK0": "0c000c00800c0000"
	},
	{
		"TYPE": "CI_FADE",
		"UNK0": "0c001000ffffff0000000400"
	},
	{
		"TYPE": "CI_LOAD",
		"UNK0": "10000c00524e0400"
	},
	{
		"TYPE": "CI_LOAD_WAIT",
		"UNK0": "0c000a000400"
	},
	{
		"TYPE": "PAGE",
		"UNK0": "0c000e0000000b007700"
	},
	{
		"TYPE": "SPEAKER",
		"UNK0": "10000a00",
		"CHARACTER_ID": 7,
		"NAME": "Kuroda Kunio"
	},
	{
		"STRINGS": [
			"\"どこかで拾ったボロ布を野生動物が被ってしまって",
			"　もがいているんだよ。",
			"　ねえ君。クラクションを鳴らしてくれないか\""
		]
	},
	{
		"TYPE": "BR",
		"UNK0": "38000a000103"
	},
	{
		"TYPE": "PAGEtm",
		"UNK0": "0c000800"
	},
	{
		"TYPE": "EXTEND",
		"UNK0": "0800180002000000000000000000000000000000"
	},
	{
		"TYPE": "EXTEND",
		"UNK0": "1800180002000000000000000000000000000000"
	},
	{
		"TYPE": "TXTWND_OUT",
		"UNK0": "18000a001400"
	},
	{
		"TYPE": "WAIT",
		"UNK0": "0c000a001e00"
	},
	{
		"TYPE": "CI_FADE",
		"UNK0": "0c001000ffffff0014000100"
	},
	{
		"TYPE": "WAIT",
		"UNK0": "10000a001400"
	},
	{
		"TYPE": "CI_FADE",
		"UNK0": "0c001000ffffff0000000100"
	},
	{
		"TYPE": "CI_LOAD",
		"UNK0": "10000c00940c0100"
	},
	{
		"TYPE": "BG_FADE",
		"UNK0": "0c001000404040801e000300"
	},
	{
		"TYPE": "WAIT",
		"UNK0": "10000a001e00"
	},
	{
		"TYPE": "SE_PLAY",
		"UNK0": "0c000e002c0280800000"
	},
	{
		"TYPE": "WAIT",
		"UNK0": "10000a003c00"
	},
	{
		"TYPE": "CI_LOAD",
		"UNK0": "0c000c00524e0400"
	},
	{
		"TYPE": "CI_LOAD_WAIT",
		"UNK0": "0c000a000400"
	},
	{
		"TYPE": "CI_MOVE",
		"UNK0": "0c0012002c01ceff400600000400"
	},
	{
		"TYPE": "CI_FADE",
		"UNK0": "140010008080800000000400"
	},
	{
		"TYPE": "CI_FADE",
		"UNK0": "10001000808080801e000400"
	},
	{
		"TYPE": "CI_MOVE",
		"UNK0": "100012001801ceff40063c000400"
	},
	{
		"TYPE": "WAIT",
		"UNK0": "14000a005000"
	},
	{
		"TYPE": "CI_MOVE",
		"UNK0": "0c0012002c01ceff400646000400"
	},
	{
		"TYPE": "WAIT",
		"UNK0": "14000a005000"
	},
	{
		"TYPE": "CI_MOVE",
		"UNK0": "0c0012001801ceff400632000400"
	},
	{
		"TYPE": "WAIT",
		"UNK0": "14000a004600"
	},
	{
		"TYPE": "CI_MOVE",
		"UNK0": "0c0012002c01ceff400650000400"
	},
	{
		"TYPE": "WAIT",
		"UNK0": "14000a005a00"
	},
	{
		"TYPE": "TXTWND_IN",
		"UNK0": "0c000a001400"
	},
	{
		"TYPE": "WAIT",
		"UNK0": "0c000a001e00"
	},
	{
		"TYPE": "PAGE",
		"UNK0": "0c000e0000000b007800"
	},
	{
		"STRINGS": [
			"目の前の『それ』はクラクションに反応して",
			"もぞもぞと動いた。"
		]
	},
	{
		"TYPE": "BR",
		"UNK0": "20000a000103"
	},
	{
		"TYPE": "PAGEtm",
		"UNK0": "0c000800"
	},
	{
		"TYPE": "CI_MOVE",
		"UNK0": "080012004001ceff40063c000400"
	},
	{
		"TYPE": "WAIT",
		"UNK0": "14000a003c00"
	},
	{
		"TYPE": "PAGE",
		"UNK0": "0c000e0000000b007900"
	},
	{
		"STRINGS": [
			"あっちへもぞもぞ"
		]
	},
	{
		"TYPE": "BR",
		"UNK0": "20000a000103"
	},
	{
		"TYPE": "PAGEtm",
		"UNK0": "0c000800"
	},
	{
		"TYPE": "CI_MOVE",
		"UNK0": "080012002c01ceff40063c000400"
	},
	{
		"TYPE": "WAIT",
		"UNK0": "14000a003c00"
	},
	{
		"TYPE": "PAGE",
		"UNK0": "0c000e0000000b007a00"
	},
	{
		"STRINGS": [
			"こっちへもぞもぞ"
		]
	},
	{
		"TYPE": "BR",
		"UNK0": "20000a000103"
	},
	{
		"TYPE": "PAGEtm",
		"UNK0": "0c000800"
	},
	{
		"TYPE": "PAGE",
		"UNK0": "08000e0000000b007b00"
	},
	{
		"STRINGS": [
			"まるで自分の位置がわからないかのようだ。"
		]
	},
	{
		"TYPE": "BR",
		"UNK0": "38000a000103"
	},
	{
		"TYPE": "PAGEtm",
		"UNK0": "0c000800"
	},
	{
		"TYPE": "CI_FADE",
		"UNK0": "08001000808080001e000400"
	},
	{
		"TYPE": "WAIT",
		"UNK0": "10000a001e00"
	},
	{
		"TYPE": "BG_FADE",
		"UNK0": "0c001000808080801e000300"
	},
	{
		"TYPE": "WAIT",
		"UNK0": "10000a001e00"
	},
	{
		"TYPE": "CI_LOAD_WAIT",
		"UNK0": "0c000a000300"
	},
	{
		"TYPE": "CI_BUSTUP_CENTERING",
		"UNK0": "0c0010000000050703000000"
	},
	{
		"TYPE": "CI_FADE",
		"UNK0": "10001000ffffffff14000300"
	},
	{
		"TYPE": "WAIT",
		"UNK0": "10000a001400"
	},
	{
		"TYPE": "PAGE",
		"UNK0": "0c000e0000000b007c00"
	},
	{
		"TYPE": "SPEAKER",
		"UNK0": "10000a00",
		"CHARACTER_ID": 7,
		"NAME": "Kuroda Kunio"
	},
	{
		"STRINGS": [
			"\"なんなんだよ、気持ち悪いな、まったく\""
		]
	},
	{
		"TYPE": "BR",
		"UNK0": "34000a000103"
	},
	{
		"TYPE": "PAGEtm",
		"UNK0": "0c000800"
	},
	{
		"TYPE": "PAGE",
		"UNK0": "08000e0000000b007d00"
	},
	{
		"TYPE": "SPEAKER",
		"UNK0": "10000a00",
		"CHARACTER_ID": 7,
		"NAME": "Kuroda Kunio"
	},
	{
		"STRINGS": [
			"\"時間を無駄にするわけにもいかないんだ。",
			"　ちょっと見てくるから、そこで待ってて\""
		]
	},
	{
		"TYPE": "BR",
		"UNK0": "34000a000103"
	},
	{
		"TYPE": "PAGEtm",
		"UNK0": "0c000800"
	},
	{
		"TYPE": "EXTEND",
		"UNK0": "0800180002000000000000000000000000000000"
	},
	{
		"TYPE": "CI_FADE",
		"UNK0": "18001000ffffff0014000300"
	},
	{
		"TYPE": "WAIT",
		"UNK0": "10000a001400"
	},
	{
		"TYPE": "CI_FADE",
		"UNK0": "0c001000ffffff0000000300"
	},
	{
		"TYPE": "CI_LOAD",
		"UNK0": "10000c00d8130300"
	},
	{
		"TYPE": "CI_FADE",
		"UNK0": "0c001000ffffff0000000400"
	},
	{
		"TYPE": "CI_LOAD",
		"UNK0": "10000c00524e0400"
	},
	{
		"TYPE": "CI_LOAD_WAIT",
		"UNK0": "0c000a000400"
	},
	{
		"TYPE": "SE_PLAY",
		"UNK0": "0c000e00320180800000"
	},
	{
		"TYPE": "WAIT",
		"UNK0": "10000a003c00"
	},
	{
		"TYPE": "SE_PLAY",
		"UNK0": "0c000e00330180800000"
	},
	{
		"TYPE": "MSG_STOP",
		"UNK0": "10000a000000"
	},
	{
		"TYPE": "MSG_READY",
		"UNK0": "0c000c000000a103"
	},
	{
		"TYPE": "MSG_WAIT",
		"UNK0": "0c000a000000"
	},
	{
		"TYPE": "MSG_PLAY",
		"UNK0": "0c000e000000a1033200"
	},
	{
		"TYPE": "WAIT",
		"UNK0": "10000a005a00"
	},
	{
		"TYPE": "MSG_VOL",
		"UNK0": "0c000e0000005a000000"
	},
	{
		"TYPE": "PAGE",
		"UNK0": "10000e0000000b007e00"
	},
	{
		"STRINGS": [
			"黒田課長は、助手席の扉を開けて外に出た。",
			"そしてゆっくりと『それ』に近づいていく。"
		]
	},
	{
		"TYPE": "BR",
		"UNK0": "34000a000103"
	},
	{
		"TYPE": "PAGEtm",
		"UNK0": "0c000800"
	},
	{
		"TYPE": "PAGE",
		"UNK0": "08000e0000000b007f00"
	},
	{
		"TYPE": "SPEAKER",
		"UNK0": "10000a00",
		"CHARACTER_ID": 6,
		"NAME": "Houjou Saki"
	},
	{
		"STRINGS": [
			"\"なんなんでしょうかね……アレ\""
		]
	},
	{
		"TYPE": "BR",
		"UNK0": "2c000a000103"
	},
	{
		"TYPE": "PAGEtm",
		"UNK0": "0c000800"
	},
	{
		"TYPE": "EXTEND",
		"UNK0": "0800180002000000000000000000000000000000"
	},
	{
		"TYPE": "CI_LOAD_WAIT",
		"UNK0": "18000a000000"
	},
	{
		"TYPE": "CI_BUSTUP_CENTERING",
		"UNK0": "0c0010000000080700000000"
	},
	{
		"TYPE": "CI_FADE",
		"UNK0": "10001000ffffffff14000000"
	},
	{
		"TYPE": "WAIT",
		"UNK0": "10000a001400"
	},
	{
		"TYPE": "WAIT",
		"UNK0": "0c000a003c00"
	},
	{
		"TYPE": "MSG_STOP",
		"UNK0": "0c000a000000"
	},
	{
		"TYPE": "CI_LOAD_WAIT",
		"UNK0": "0c000a000100"
	},
	{
		"TYPE": "CI_BUSTUP_CENTERING",
		"UNK0": "0c0010000000070701000000"
	},
	{
		"TYPE": "CI_FADE",
		"UNK0": "10001000ffffffff00000100"
	},
	{
		"TYPE": "WAIT",
		"UNK0": "10000a000000"
	},
	{
		"TYPE": "CI_FADE",
		"UNK0": "0c001000ffffff0000000000"
	},
	{
		"TYPE": "WAIT",
		"UNK0": "10000a000000"
	},
	{
		"TYPE": "WAIT",
		"UNK0": "0c000a001e00"
	},
	{
		"TYPE": "PAGE",
		"UNK0": "0c000e0000000b008000"
	},
	{
		"STRINGS": [
			"その時なぜか、関本爽二朗は口角をあげて笑った。"
		]
	},
	{
		"TYPE": "BR",
		"UNK0": "40000a000103"
	},
	{
		"TYPE": "PAGEtm",
		"UNK0": "0c000800"
	},
	{
		"TYPE": "PAGE",
		"UNK0": "08000e0000000b008100"
	},
	{
		"STRINGS": [
			"––いま、どうして笑ったの？"
		]
	},
	{
		"TYPE": "BR",
		"UNK0": "2c000a000103"
	},
	{
		"TYPE": "PAGEtm",
		"UNK0": "0c000800"
	},
	{
		"TYPE": "CI_FADE",
		"UNK0": "08001000ffffff0014000100"
	},
	{
		"TYPE": "WAIT",
		"UNK0": "10000a001400"
	},
	{
		"TYPE": "CI_FADE",
		"UNK0": "0c001000ffffff0000000100"
	},
	{
		"TYPE": "SCR_VIB",
		"UNK0": "10000e000f0001010f00"
	},
	{
		"TYPE": "PAGE",
		"UNK0": "10000e0000000b008200"
	},
	{
		"TYPE": "SPEAKER",
		"UNK0": "10000a00",
		"CHARACTER_ID": 7,
		"NAME": "Kuroda Kunio"
	},
	{
		"STRINGS": [
			"\"うわああっ！\""
		]
	},
	{
		"TYPE": "BR",
		"UNK0": "1c000a000103"
	},
	{
		"TYPE": "PAGEtm",
		"UNK0": "0c000800"
	},
	{
		"TYPE": "EXTEND",
		"UNK0": "0800180002000000000000000000000000000000"
	},
	{
		"TYPE": "BGM_PLAY",
		"UNK0": "18000c000a000100"
	},
	{
		"TYPE": "BGM_VOL",
		"UNK0": "0c000c0000008000"
	},
	{
		"TYPE": "WAIT",
		"UNK0": "0c000a003c00"
	},
	{
		"TYPE": "PAGE",
		"UNK0": "0c000e0000000b008300"
	},
	{
		"STRINGS": [
			"突然、前方の黒田課長が叫び声を上げた。"
		]
	},
	{
		"TYPE": "BR",
		"UNK0": "38000a000103"
	},
	{
		"TYPE": "PAGEtm",
		"UNK0": "0c000800"
	},
	{
		"TYPE": "PAGE",
		"UNK0": "08000e0000000b008400"
	},
	{
		"STRINGS": [
			"その声に弾かれるように私は振り向くと、",
			"黒田課長は腰を抜かしていた。"
		]
	},
	{
		"TYPE": "BR",
		"UNK0": "28000a000103"
	},
	{
		"TYPE": "PAGEtm",
		"UNK0": "0c000800"
	},
	{
		"TYPE": "PAGE",
		"UNK0": "08000e0000000b008500"
	},
	{
		"TYPE": "SPEAKER",
		"UNK0": "10000a00",
		"CHARACTER_ID": 7,
		"NAME": "Kuroda Kunio"
	},
	{
		"STRINGS": [
			"\"北條クン、北條クン！！",
			"　署に連絡だ！　応援を頼んで！！\""
		]
	},
	{
		"TYPE": "BR",
		"UNK0": "30000a000103"
	},
	{
		"TYPE": "PAGEtm",
		"UNK0": "0c000800"
	},
	{
		"TYPE": "EXTEND",
		"UNK0": "0800180002000000000000000000000000000000"
	},
	{
		"TYPE": "PAGE",
		"UNK0": "18000e0000000b008600"
	},
	{
		"TYPE": "SPEAKER",
		"UNK0": "10000a00",
		"CHARACTER_ID": 6,
		"NAME": "Houjou Saki"
	},
	{
		"STRINGS": [
			"\"黒田課長！？　どうしたんですか！\""
		]
	},
	{
		"TYPE": "BR",
		"UNK0": "30000a000103"
	},
	{
		"TYPE": "PAGEtm",
		"UNK0": "0c000800"
	},
	{
		"TYPE": "EXTEND",
		"UNK0": "0800180002000000000000000000000000000000"
	},
	{
		"TYPE": "PAGE",
		"UNK0": "18000e0000000b008700"
	},
	{
		"TYPE": "SPEAKER",
		"UNK0": "10000a00",
		"CHARACTER_ID": 7,
		"NAME": "Kuroda Kunio"
	},
	{
		"STRINGS": [
			"\"奴だ！　奴が出た！！\""
		]
	},
	{
		"TYPE": "BR",
		"UNK0": "24000a000103"
	},
	{
		"TYPE": "PAGEtm",
		"UNK0": "0c000800"
	},
	{
		"TYPE": "EXTEND",
		"UNK0": "0800180002000000000000000000000000000000"
	},
	{
		"TYPE": "PAGE",
		"UNK0": "18000e0000000b008800"
	},
	{
		"TYPE": "SPEAKER",
		"UNK0": "10000a00",
		"CHARACTER_ID": 6,
		"NAME": "Houjou Saki"
	},
	{
		"STRINGS": [
			"\"すいません、私も出ます！",
			"　あなたはここにいて！\""
		]
	},
	{
		"TYPE": "BR",
		"UNK0": "24000a000103"
	},
	{
		"TYPE": "PAGEtm",
		"UNK0": "0c000800"
	},
	{
		"TYPE": "EXTEND",
		"UNK0": "0800180002000000000000000000000000000000"
	},
	{
		"TYPE": "EXTEND",
		"UNK0": "1800180002000000000000000000000000000000"
	},
	{
		"TYPE": "TXTWND_OUT",
		"UNK0": "18000a001400"
	},
	{
		"TYPE": "WAIT",
		"UNK0": "0c000a001e00"
	},
	{
		"TYPE": "SE_PLAY",
		"UNK0": "0c000e00300180800000"
	},
	{
		"TYPE": "LOOPS_VOL",
		"UNK0": "10000e005a003c000000"
	},
	{
		"TYPE": "SCR_FADE",
		"UNK0": "10001000000000803c000000"
	},
	{
		"TYPE": "WAIT",
		"UNK0": "10000a003c00"
	},
	{
		"TYPE": "BG_FADE",
		"UNK0": "0c0010000000000000000300"
	},
	{
		"TYPE": "BG_MOVE",
		"UNK0": "1000120000000000d00700000300"
	},
	{
		"TYPE": "BG_SET_ADJUST_Z",
		"UNK0": "14000c0003000300"
	},
	{
		"TYPE": "BG_LOAD",
		"UNK0": "0c000c0094110300"
	},
	{
		"TYPE": "BG_WAIT",
		"UNK0": "0c000a000000"
	},
	{
		"TYPE": "BG_SET_ADJUST_Z",
		"UNK0": "0c000c0000000000"
	},
	{
		"TYPE": "BG_FADE",
		"UNK0": "0c001000ffffffff00000000"
	},
	{
		"TYPE": "SE_PLAY",
		"UNK0": "10000e00310180800000"
	},
	{
		"TYPE": "SCR_FADE",
		"UNK0": "10001000000000003c000000"
	},
	{
		"TYPE": "WAIT",
		"UNK0": "10000a003c00"
	},
	{
		"TYPE": "WAIT",
		"UNK0": "0c000a005000"
	},
	{
		"TYPE": "MSG_STOP",
		"UNK0": "0c000a000100"
	},
	{
		"TYPE": "MSG_READY",
		"UNK0": "0c000c000100a303"
	},
	{
		"TYPE": "MSG_WAIT",
		"UNK0": "0c000a000100"
	},
	{
		"TYPE": "MSG_PLAY",
		"UNK0": "0c000e000100a303c800"
	},
	{
		"TYPE": "WAIT",
		"UNK0": "10000a003c00"
	},
	{
		"TYPE": "LOOPS_WAIT",
		"UNK0": "0c000a000100"
	},
	{
		"TYPE": "LOOPS_PLAY",
		"UNK0": "0c001000f302000000000100"
	},
	{
		"TYPE": "LOOPS_VOL",
		"UNK0": "10000e0046003c000100"
	},
	{
		"TYPE": "LOOPS_VOL",
		"UNK0": "10000e0000003c000000"
	},
	{
		"TYPE": "WAIT",
		"UNK0": "10000a003c00"
	},
	{
		"TYPE": "LOOPS_VOL",
		"UNK0": "0c000e00000000000000"
	},
	{
		"TYPE": "LOOPS_STOP",
		"UNK0": "10000a000000"
	},
	{
		"TYPE": "TXTWND_IN",
		"UNK0": "0c000a001400"
	},
	{
		"TYPE": "WAIT",
		"UNK0": "0c000a001e00"
	},
	{
		"TYPE": "PAGE",
		"UNK0": "0c000e0000000b008900"
	},
	{
		"STRINGS": [
			"私は黒田課長のもとにかけつけた。",
			"彼はいまだに驚きおののいていた。"
		]
	},
	{
		"TYPE": "BR",
		"UNK0": "2c000a000103"
	},
	{
		"TYPE": "PAGEtm",
		"UNK0": "0c000800"
	},
	{
		"TYPE": "PAGE",
		"UNK0": "08000e0000000b008a00"
	},
	{
		"TYPE": "SPEAKER",
		"UNK0": "10000a00",
		"CHARACTER_ID": 6,
		"NAME": "Houjou Saki"
	},
	{
		"STRINGS": [
			"\"黒田課長！\""
		]
	},
	{
		"TYPE": "BR",
		"UNK0": "1c000a000103"
	},
	{
		"TYPE": "PAGEtm",
		"UNK0": "0c000800"
	},
	{
		"TYPE": "EXTEND",
		"UNK0": "0800180002000000000000000000000000000000"
	},
	{
		"TYPE": "CI_LOAD_WAIT",
		"UNK0": "18000a000300"
	},
	{
		"TYPE": "CI_BUSTUP_CENTERING",
		"UNK0": "0c0010000000050703000000"
	},
	{
		"TYPE": "CI_FADE",
		"UNK0": "10001000ffffffff14000300"
	},
	{
		"TYPE": "WAIT",
		"UNK0": "10000a001400"
	},
	{
		"TYPE": "PAGE",
		"UNK0": "0c000e0000000b008b00"
	},
	{
		"TYPE": "SPEAKER",
		"UNK0": "10000a00",
		"CHARACTER_ID": 7,
		"NAME": "Kuroda Kunio"
	},
	{
		"STRINGS": [
			"\"こ、こ、こここれ……！？\""
		]
	},
	{
		"TYPE": "BR",
		"UNK0": "28000a000103"
	},
	{
		"TYPE": "PAGEtm",
		"UNK0": "0c000800"
	},
	{
		"TYPE": "EXTEND",
		"UNK0": "0800180002000000000000000000000000000000"
	},
	{
		"TYPE": "CI_FADE",
		"UNK0": "18001000ffffff0014000300"
	},
	{
		"TYPE": "WAIT",
		"UNK0": "10000a001400"
	},
	{
		"TYPE": "CI_FADE",
		"UNK0": "0c001000ffffff0000000300"
	},
	{
		"TYPE": "CI_LOAD",
		"UNK0": "10000c00524e0400"
	},
	{
		"TYPE": "CI_LOAD_WAIT",
		"UNK0": "0c000a000400"
	},
	{
		"TYPE": "CI_MOVE",
		"UNK0": "0c0012004001ceff400600000400"
	},
	{
		"TYPE": "CI_FADE",
		"UNK0": "140010008080800000000400"
	},
	{
		"TYPE": "CI_FADE",
		"UNK0": "10001000808080801e000400"
	},
	{
		"TYPE": "CI_MOVE",
		"UNK0": "100012002c01ceff40065a000400"
	},
	{
		"TYPE": "WAIT",
		"UNK0": "14000a005a00"
	},
	{
		"TYPE": "PAGE",
		"UNK0": "0c000e0000000b008c00"
	},
	{
		"STRINGS": [
			"彼が指さした先にあったのは、",
			"例のボロ布をまとった『それ』だった。"
		]
	},
	{
		"TYPE": "BR",
		"UNK0": "30000a000103"
	},
	{
		"TYPE": "PAGEtm",
		"UNK0": "0c000800"
	},
	{
		"TYPE": "PAGE",
		"UNK0": "08000e0000000b008d00"
	},
	{
		"STRINGS": [
			"私達の気配に気付いているのか、",
			"いまだにもぞもぞと動いている。"
		]
	},
	{
		"TYPE": "BR",
		"UNK0": "2c000a000103"
	},
	{
		"TYPE": "PAGEtm",
		"UNK0": "0c000800"
	},
	{
		"TYPE": "EXTEND",
		"UNK0": "0800180002000000000000000000000000000000"
	},
	{
		"TYPE": "TXTWND_OUT",
		"UNK0": "18000a001400"
	},
	{
		"TYPE": "WAIT",
		"UNK0": "0c000a001e00"
	},
	{
		"TYPE": "SE_PLAY",
		"UNK0": "0c000e00a90080800000"
	},
	{
		"TYPE": "CI_LOAD",
		"UNK0": "10000c00524e0500"
	},
	{
		"TYPE": "CI_LOAD_WAIT",
		"UNK0": "0c000a000500"
	},
	{
		"TYPE": "CI_MOVE",
		"UNK0": "0c0012002c01ceff3f0600000500"
	},
	{
		"TYPE": "CI_FADE",
		"UNK0": "140010008080800000000500"
	},
	{
		"TYPE": "CI_FADE",
		"UNK0": "10001000808080005a000400"
	},
	{
		"TYPE": "CI_FADE",
		"UNK0": "10001000808080805a000500"
	},
	{
		"TYPE": "CI_SIZE",
		"UNK0": "100010001001400428000500"
	},
	{
		"TYPE": "WAIT",
		"UNK0": "10000a000500"
	},
	{
		"TYPE": "CI_MOVE",
		"UNK0": "0c0012001801ceff3f065a000500"
	},
	{
		"TYPE": "WAIT",
		"UNK0": "14000a005a00"
	},
	{
		"TYPE": "TXTWND_IN",
		"UNK0": "0c000a001400"
	},
	{
		"TYPE": "WAIT",
		"UNK0": "0c000a001e00"
	},
	{
		"TYPE": "PAGE",
		"UNK0": "0c000e0000000b008e00"
	},
	{
		"STRINGS": [
			"その動きはとてもゆっくりとしていた。",
			"うまく動けないのか、足を引きずるような音がする。"
		]
	},
	{
		"TYPE": "BR",
		"UNK0": "3c000a000103"
	},
	{
		"TYPE": "PAGEtm",
		"UNK0": "0c000800"
	},
	{
		"TYPE": "PAGE",
		"UNK0": "08000e0000000b008f00"
	},
	{
		"STRINGS": [
			"同時に、かすかな臭いが私の鼻腔をくすぐった。",
			"それは、舌の中でぬるりとした金属の感触を思い起こさせた。"
		]
	},
	{
		"TYPE": "BR",
		"UNK0": "44000a000103"
	},
	{
		"TYPE": "PAGEtm",
		"UNK0": "0c000800"
	},
	{
		"TYPE": "PAGE",
		"UNK0": "08000e0000000b009000"
	},
	{
		"STRINGS": [
			"まさか……血？",
			"『それ』の足下を確認する。"
		]
	},
	{
		"TYPE": "BR",
		"UNK0": "28000a000103"
	},
	{
		"TYPE": "PAGEtm",
		"UNK0": "0c000800"
	},
	{
		"TYPE": "PAGE",
		"UNK0": "08000e0000000b009100"
	},
	{
		"STRINGS": [
			"暗闇に紛れて判然としないが、濃色の液体がぽたぽたと",
			"地面を濡らしていた。"
		]
	},
	{
		"TYPE": "BR",
		"UNK0": "20000a000103"
	},
	{
		"TYPE": "PAGEtm",
		"UNK0": "0c000800"
	},
	{
		"TYPE": "PAGE",
		"UNK0": "08000e0000000b009200"
	},
	{
		"TYPE": "SPEAKER",
		"UNK0": "10000a00",
		"CHARACTER_ID": 6,
		"NAME": "Houjou Saki"
	},
	{
		"STRINGS": [
			"\"……あなた、怪我をしているの？\""
		]
	},
	{
		"TYPE": "BR",
		"UNK0": "30000a000103"
	},
	{
		"TYPE": "PAGEtm",
		"UNK0": "0c000800"
	},
	{
		"TYPE": "EXTEND",
		"UNK0": "0800180002000000000000000000000000000000"
	},
	{
		"TYPE": "SCR_VIB",
		"UNK0": "18000e000f0001010f00"
	},
	{
		"TYPE": "PAGE",
		"UNK0": "10000e0000000b009300"
	},
	{
		"TYPE": "SPEAKER",
		"UNK0": "10000a00",
		"CHARACTER_ID": 1,
		"NAME": "???"
	},
	{
		"STRINGS": [
			"\"う……ううう……う……\""
		]
	},
	{
		"TYPE": "BR",
		"UNK0": "28000a000103"
	},
	{
		"TYPE": "PAGEtm",
		"UNK0": "0c000800"
	},
	{
		"TYPE": "EXTEND",
		"UNK0": "0800180002000000000000000000000000000000"
	},
	{
		"TYPE": "PAGE",
		"UNK0": "18000e0000000b009400"
	},
	{
		"STRINGS": [
			"うめき声も布の中から聞こえてくる。",
			"その声を聞いて、私は直感した。"
		]
	},
	{
		"TYPE": "BR",
		"UNK0": "2c000a000103"
	},
	{
		"TYPE": "PAGEtm",
		"UNK0": "0c000800"
	},
	{
		"TYPE": "PAGE",
		"UNK0": "08000e0000000b009500"
	},
	{
		"TYPE": "SPEAKER",
		"UNK0": "10000a00",
		"CHARACTER_ID": 6,
		"NAME": "Houjou Saki"
	},
	{
		"STRINGS": [
			"\"まさか……人？",
			"　ちょっと、ねえ、大丈夫ですか！！\""
		]
	},
	{
		"TYPE": "BR",
		"UNK0": "30000a000103"
	},
	{
		"TYPE": "PAGEtm",
		"UNK0": "0c000800"
	},
	{
		"TYPE": "EXTEND",
		"UNK0": "0800180002000000000000000000000000000000"
	},
	{
		"TYPE": "SE_PLAY",
		"UNK0": "18000e00af0180800000"
	},
	{
		"TYPE": "CI_FADE",
		"UNK0": "10001000808080001e000500"
	},
	{
		"TYPE": "CI_FADE",
		"UNK0": "10001000ffffff0000000400"
	},
	{
		"TYPE": "WAIT",
		"UNK0": "10000a001e00"
	},
	{
		"TYPE": "PAGE",
		"UNK0": "0c000e0000000b009600"
	},
	{
		"STRINGS": [
			"私が駆け寄ったその時、",
			"頭からすっぽり被っているボロ布がずるりと落ちた。"
		]
	},
	{
		"TYPE": "BR",
		"UNK0": "3c000a000103"
	},
	{
		"TYPE": "PAGEtm",
		"UNK0": "0c000800"
	},
	{
		"TYPE": "EXTEND",
		"UNK0": "0800180002000000000000000000000000000000"
	},
	{
		"TYPE": "TXTWND_OUT",
		"UNK0": "18000a001400"
	},
	{
		"TYPE": "WAIT",
		"UNK0": "0c000a001e00"
	},
	{
		"TYPE": "BGM_VOL",
		"UNK0": "0c000c003c000000"
	},
	{
		"TYPE": "LOOPS_VOL",
		"UNK0": "0c000e0000003c000100"
	},
	{
		"TYPE": "WAIT",
		"UNK0": "10000a003c00"
	},
	{
		"TYPE": "BGM_VOL",
		"UNK0": "0c000c0000000000"
	},
	{
		"TYPE": "BGM_STOP",
		"UNK0": "0c000800"
	},
	{
		"TYPE": "LOOPS_VOL",
		"UNK0": "08000e00000000000100"
	},
	{
		"TYPE": "LOOPS_STOP",
		"UNK0": "10000a000100"
	},
	{
		"TYPE": "SE_PLAY",
		"UNK0": "0c000e00f50080800000"
	},
	{
		"TYPE": "BG_WAIT",
		"UNK0": "10000a000100"
	},
	{
		"TYPE": "BG_SET_ADJUST_Z",
		"UNK0": "0c000c0001000100"
	},
	{
		"TYPE": "BG_FADE",
		"UNK0": "0c0010008080808000000100"
	},
	{
		"TYPE": "BG_SIZE",
		"UNK0": "10001000000aa00500000100"
	},
	{
		"TYPE": "BG_MOVE",
		"UNK0": "1000120000fe00000e0600000100"
	},
	{
		"TYPE": "BG_WAIT",
		"UNK0": "14000a000300"
	},
	{
		"TYPE": "BG_SET_ADJUST_Z",
		"UNK0": "0c000c0003000300"
	},
	{
		"TYPE": "BG_FADE",
		"UNK0": "0c0010008080800000000300"
	},
	{
		"TYPE": "BG_MOVE",
		"UNK0": "1000120000000000dc0500000300"
	},
	{
		"TYPE": "WAIT",
		"UNK0": "14000a000500"
	},
	{
		"TYPE": "BG_SIZE",
		"UNK0": "0c0010000005d0020a000100"
	},
	{
		"TYPE": "BG_MOVE",
		"UNK0": "10001200000000000e060a000100"
	},
	{
		"TYPE": "BG_WAIT",
		"UNK0": "14000a000200"
	},
	{
		"TYPE": "BG_SET_ADJUST_Z",
		"UNK0": "0c000c0002000200"
	},
	{
		"TYPE": "BG_FADE",
		"UNK0": "0c001000808080300a000200"
	},
	{
		"TYPE": "BG_MOVE",
		"UNK0": "1000120005000500fa0500000200"
	},
	{
		"TYPE": "WAIT",
		"UNK0": "14000a000a00"
	},
	{
		"TYPE": "BG_FADE",
		"UNK0": "0c001000808080000a000200"
	},
	{
		"TYPE": "SCR_VIB",
		"UNK0": "10000e000f0001010f00"
	},
	{
		"TYPE": "SE_PLAY",
		"UNK0": "10000e00640080800000"
	},
	{
		"TYPE": "CI_FADE",
		"UNK0": "10001000ffffff0000000400"
	},
	{
		"TYPE": "CI_FADE",
		"UNK0": "10001000ffffff0000000500"
	},
	{
		"TYPE": "PAD_VIB",
		"UNK0": "10000e001e000001c800"
	},
	{
		"TYPE": "BG_FADE",
		"UNK0": "100010008080801005000300"
	},
	{
		"TYPE": "WAIT",
		"UNK0": "10000a000500"
	},
	{
		"TYPE": "BG_FADE",
		"UNK0": "0c0010008080800005000300"
	},
	{
		"TYPE": "WAIT",
		"UNK0": "10000a006400"
	},
	{
		"TYPE": "BG_FADE",
		"UNK0": "0c0010000000000000000200"
	},
	{
		"TYPE": "BG_MOVE",
		"UNK0": "1000120000000000d00700000200"
	},
	{
		"TYPE": "BG_SET_ADJUST_Z",
		"UNK0": "14000c0002000200"
	},
	{
		"TYPE": "BG_FADE",
		"UNK0": "0c0010000000000000000300"
	},
	{
		"TYPE": "BG_MOVE",
		"UNK0": "1000120000000000d00700000300"
	},
	{
		"TYPE": "BG_SET_ADJUST_Z",
		"UNK0": "14000c0003000300"
	},
	{
		"TYPE": "BGM_PLAY",
		"UNK0": "0c000c000f000100"
	},
	{
		"TYPE": "BGM_VOL",
		"UNK0": "0c000c0000008000"
	},
	{
		"TYPE": "WAIT",
		"UNK0": "0c000a003c00"
	},
	{
		"TYPE": "TXTWND_IN",
		"UNK0": "0c000a001400"
	},
	{
		"TYPE": "WAIT",
		"UNK0": "0c000a001e00"
	},
	{
		"TYPE": "PAGE",
		"UNK0": "0c000e0000000b009700"
	},
	{
		"TYPE": "SPEAKER",
		"UNK0": "10000a00",
		"CHARACTER_ID": 6,
		"NAME": "Houjou Saki"
	},
	{
		"STRINGS": [
			"\"……！！！\""
		]
	},
	{
		"TYPE": "BR",
		"UNK0": "1c000a000103"
	},
	{
		"TYPE": "PAGEtm",
		"UNK0": "0c000800"
	},
	{
		"TYPE": "PAGE",
		"UNK0": "08000e0000000b009800"
	},
	{
		"TYPE": "SPEAKER",
		"UNK0": "10000a00",
		"CHARACTER_ID": 6,
		"NAME": "Houjou Saki"
	},
	{
		"STRINGS": [
			"\"嘘……！？",
			"　あなた、水瀬遥……さん！？\""
		]
	},
	{
		"TYPE": "BR",
		"UNK0": "2c000a000103"
	},
	{
		"TYPE": "PAGEtm",
		"UNK0": "0c000800"
	},
	{
		"TYPE": "EXTEND",
		"UNK0": "0800180002000000000000000000000000000000"
	},
	{
		"TYPE": "PAGE",
		"UNK0": "18000e0000000b009900"
	},
	{
		"TYPE": "SPEAKER",
		"UNK0": "10000a00",
		"CHARACTER_ID": 11,
		"NAME": "Minase Haruka"
	},
	{
		"TYPE": "FONT",
		"UNK0": "0c000a000004"
	},
	{
		"STRINGS": [
			"\"う……ううう……うう……！\""
		]
	},
	{
		"TYPE": "FONTtm",
		"UNK0": "2c000800"
	},
	{
		"TYPE": "BR",
		"UNK0": "08000a000103"
	},
	{
		"TYPE": "PAGEtm",
		"UNK0": "0c000800"
	},
	{
		"TYPE": "EXTEND",
		"UNK0": "0800180002000000000000000000000000000000"
	},
	{
		"TYPE": "BG_FADE",
		"UNK0": "180010000000000000000000"
	},
	{
		"TYPE": "BG_MOVE",
		"UNK0": "1000120000000000d00700000000"
	},
	{
		"TYPE": "BG_SET_ADJUST_Z",
		"UNK0": "14000c0000000000"
	},
	{
		"TYPE": "PAGE",
		"UNK0": "0c000e0000000b009a00"
	},
	{
		"TYPE": "FONT",
		"UNK0": "10000a000004"
	},
	{
		"STRINGS": [
			"遥さんは両目のあたりが真っ赤になっていた。"
		]
	},
	{
		"TYPE": "FONTtm",
		"UNK0": "38000800"
	},
	{
		"TYPE": "BR",
		"UNK0": "08000a000000"
	},
	{
		"TYPE": "FONT",
		"UNK0": "0c000a000004"
	},
	{
		"STRINGS": [
			"痛みで苦しいのか、まるで赤子のように"
		]
	},
	{
		"TYPE": "FONTtm",
		"UNK0": "30000800"
	},
	{
		"TYPE": "BR",
		"UNK0": "08000a000000"
	},
	{
		"TYPE": "FONT",
		"UNK0": "0c000a000004"
	},
	{
		"STRINGS": [
			"ひくひくともがくばかりだ。"
		]
	},
	{
		"TYPE": "FONTtm",
		"UNK0": "28000800"
	},
	{
		"TYPE": "BR",
		"UNK0": "08000a000103"
	},
	{
		"TYPE": "PAGEtm",
		"UNK0": "0c000800"
	},
	{
		"TYPE": "PAGE",
		"UNK0": "08000e0000000b009b00"
	},
	{
		"TYPE": "FONT",
		"UNK0": "10000a000004"
	},
	{
		"STRINGS": [
			"ブラインドマンが彼女に手をかけたのは明白だった。"
		]
	},
	{
		"TYPE": "FONTtm",
		"UNK0": "3c000800"
	},
	{
		"TYPE": "BR",
		"UNK0": "08000a000103"
	},
	{
		"TYPE": "PAGEtm",
		"UNK0": "0c000800"
	},
	{
		"TYPE": "PAGE",
		"UNK0": "08000e0000000b009c00"
	},
	{
		"TYPE": "SPEAKER",
		"UNK0": "10000a00",
		"CHARACTER_ID": 6,
		"NAME": "Houjou Saki"
	},
	{
		"STRINGS": [
			"\"いったい誰にやられたんですか！！\""
		]
	},
	{
		"TYPE": "BR",
		"UNK0": "30000a000103"
	},
	{
		"TYPE": "PAGEtm",
		"UNK0": "0c000800"
	},
	{
		"TYPE": "EXTEND",
		"UNK0": "0800180002000000000000000000000000000000"
	},
	{
		"TYPE": "PAGE",
		"UNK0": "18000e0000000b009d00"
	},
	{
		"TYPE": "SPEAKER",
		"UNK0": "10000a00",
		"CHARACTER_ID": 11,
		"NAME": "Minase Haruka"
	},
	{
		"TYPE": "FONT",
		"UNK0": "0c000a000004"
	},
	{
		"STRINGS": [
			"\"ううう……ううううう……！\""
		]
	},
	{
		"TYPE": "FONTtm",
		"UNK0": "2c000800"
	},
	{
		"TYPE": "BR",
		"UNK0": "08000a000103"
	},
	{
		"TYPE": "PAGEtm",
		"UNK0": "0c000800"
	},
	{
		"TYPE": "EXTEND",
		"UNK0": "0800180002000000000000000000000000000000"
	},
	{
		"TYPE": "PAGE",
		"UNK0": "18000e0000000b009e00"
	},
	{
		"TYPE": "SPEAKER",
		"UNK0": "10000a00",
		"CHARACTER_ID": 6,
		"NAME": "Houjou Saki"
	},
	{
		"STRINGS": [
			"\"ブラインドマンにやられたんですよね！",
			"　あいつはどこに行ったんですか！？\""
		]
	},
	{
		"TYPE": "BR",
		"UNK0": "30000a000103"
	},
	{
		"TYPE": "PAGEtm",
		"UNK0": "0c000800"
	},
	{
		"TYPE": "PAGE",
		"UNK0": "08000e0000000b009f00"
	},
	{
		"STRINGS": [
			"私の問い掛けにまったく反応を示さない。",
			"いや、答える事が出来ないのだ。"
		]
	},
	{
		"TYPE": "BR",
		"UNK0": "2c000a000103"
	},
	{
		"TYPE": "PAGEtm",
		"UNK0": "0c000800"
	},
	{
		"TYPE": "PAGE",
		"UNK0": "08000e0000000b00a000"
	},
	{
		"TYPE": "FONT",
		"UNK0": "10000a000004"
	},
	{
		"STRINGS": [
			"時折、口がぱくぱくと動いて、口腔内を"
		]
	},
	{
		"TYPE": "FONTtm",
		"UNK0": "30000800"
	},
	{
		"TYPE": "BR",
		"UNK0": "08000a000000"
	},
	{
		"TYPE": "FONT",
		"UNK0": "0c000a000004"
	},
	{
		"STRINGS": [
			"見る事ができるが、"
		]
	},
	{
		"TYPE": "FONTtm",
		"UNK0": "20000800"
	},
	{
		"TYPE": "BR",
		"UNK0": "08000a000000"
	},
	{
		"TYPE": "FONT",
		"UNK0": "0c000a000004"
	},
	{
		"STRINGS": [
			"舌がざっくりと切り取られていた。"
		]
	},
	{
		"TYPE": "FONTtm",
		"UNK0": "2c000800"
	},
	{
		"TYPE": "BR",
		"UNK0": "08000a000103"
	},
	{
		"TYPE": "PAGEtm",
		"UNK0": "0c000800"
	},
	{
		"TYPE": "PAGE",
		"UNK0": "08000e0000000b00a100"
	},
	{
		"TYPE": "FONT",
		"UNK0": "10000a000004"
	},
	{
		"STRINGS": [
			"彼女は喋る事を封じられていた。"
		]
	},
	{
		"TYPE": "FONTtm",
		"UNK0": "2c000800"
	},
	{
		"TYPE": "BR",
		"UNK0": "08000a000103"
	},
	{
		"TYPE": "PAGEtm",
		"UNK0": "0c000800"
	},
	{
		"TYPE": "PAGE",
		"UNK0": "08000e0000000b00a200"
	},
	{
		"TYPE": "FONT",
		"UNK0": "10000a000004"
	},
	{
		"STRINGS": [
			"遥さんの出血はいまだ止まる様子がなかった。"
		]
	},
	{
		"TYPE": "FONTtm",
		"UNK0": "38000800"
	},
	{
		"TYPE": "BR",
		"UNK0": "08000a000000"
	},
	{
		"TYPE": "FONT",
		"UNK0": "0c000a000004"
	},
	{
		"STRINGS": [
			"ということは、被害にあってからさほど時間が"
		]
	},
	{
		"TYPE": "FONTtm",
		"UNK0": "38000800"
	},
	{
		"TYPE": "BR",
		"UNK0": "08000a000000"
	},
	{
		"TYPE": "FONT",
		"UNK0": "0c000a000004"
	},
	{
		"STRINGS": [
			"経っていないはずだ。"
		]
	},
	{
		"TYPE": "FONTtm",
		"UNK0": "20000800"
	},
	{
		"TYPE": "BR",
		"UNK0": "08000a000103"
	},
	{
		"TYPE": "PAGEtm",
		"UNK0": "0c000800"
	},
	{
		"TYPE": "PAGE",
		"UNK0": "08000e0000000b00a300"
	},
	{
		"STRINGS": [
			"遥さんの様子をもう一度確認し、",
			"私は最初になすべき事を決めた。",
			"それは——"
		]
	},
	{
		"TYPE": "BR",
		"UNK0": "18000a000103"
	},
	{
		"TYPE": "PAGEtm",
		"UNK0": "0c000800"
	},
	{
		"TYPE": "JUMP",
		"UNK0": "08000c00",
		"SCRIPT_ID": 11240
	},
	{
		"TYPE": "DEMOtm",
		"UNK0": "0c000800"
	}
]